{
  "ComponentIndexes": {},
  "ControlUniqueGuids": {},
  "ControlUniqueIds": {
    "Aceito a": 398,
    "App": 1,
    "Arrow1": 31,
    "Arrow1_1": 303,
    "Arrow2": 302,
    "Arrow2_1": 402,
    "Atividade1": 180,
    "Atividade2": 158,
    "Atividades": 232,
    "Aviso1": 356,
    "Aviso2": 336,
    "Aviso3": 93,
    "Aviso4": 137,
    "Body2": 486,
    "Button1": 264,
    "Button1_1": 266,
    "Button1_10": 424,
    "Button1_12": 191,
    "Button1_13": 326,
    "Button1_14": 366,
    "Button1_15": 462,
    "Button1_16": 127,
    "Button1_17": 345,
    "Button1_18": 103,
    "Button1_19": 147,
    "Button1_20": 169,
    "Button1_4": 443,
    "Button1_5": 401,
    "Button1_9": 83,
    "Button2": 458,
    "Button3_3": 218,
    "Button3_4": 220,
    "Button3_5": 222,
    "Button3_6": 224,
    "Button3_7": 212,
    "Button3_8": 214,
    "Button3_9": 228,
    "Button4": 506,
    "Button4_1": 510,
    "Button4_2": 55,
    "Button4_3": 51,
    "Button5": 58,
    "Button5_1": 516,
    "Button5_2": 61,
    "Button6": 243,
    "Button6_1": 250,
    "Calendario": 314,
    "Checkbox2": 397,
    "ConfirmaEmail": 17,
    "Confirmar E-mail_DataCard1": 14,
    "Confirmar Senha_DataCard1": 24,
    "ConfirmarSenha": 27,
    "CPF_DataCard1": 284,
    "Data Nascimento_DataCard1": 294,
    "DataCardKey1": 296,
    "DataCardKey10": 291,
    "DataCardKey3": 16,
    "DataCardKey4": 26,
    "DataCardKey5": 21,
    "DataCardKey6": 11,
    "DataCardKey7": 276,
    "DataCardKey8": 281,
    "DataCardKey9": 286,
    "DataCardValue10": 292,
    "DataCardValue7": 277,
    "DataCardValue8": 282,
    "DataCardValue9": 287,
    "DateValue1": 297,
    "DigitarSenha": 22,
    "E-mail": 438,
    "E-mail_DataCard1": 9,
    "entradaEmail": 12,
    "ErrorMessage1": 301,
    "ErrorMessage2": 18,
    "ErrorMessage3": 28,
    "ErrorMessage4": 23,
    "ErrorMessage5": 13,
    "ErrorMessage6": 278,
    "ErrorMessage7": 283,
    "ErrorMessage8": 288,
    "ErrorMessage9": 293,
    "Esqueci senha | Suporte": 444,
    "Facebook": 446,
    "Facebook_1": 33,
    "Facebook_10": 85,
    "Facebook_11": 426,
    "Facebook_12": 489,
    "Facebook_13": 129,
    "Facebook_14": 328,
    "Facebook_15": 347,
    "Facebook_16": 518,
    "Facebook_17": 63,
    "Facebook_18": 105,
    "Facebook_19": 149,
    "Facebook_20": 171,
    "Facebook_3": 305,
    "Facebook_4": 404,
    "Facebook_5": 464,
    "Facebook_6": 252,
    "Facebook_8": 368,
    "Facebook_9": 193,
    "Ferramentas": 229,
    "Footer_Atividade": 199,
    "Footer_Atividade_1": 177,
    "Footer_Avisos": 374,
    "Footer_Avisos_1": 353,
    "Footer_Avisos_2": 111,
    "Footer_Avisos_3": 155,
    "Footer_Calendario": 334,
    "Footer_CursoDisciplinas": 91,
    "Footer_Home": 259,
    "Footer_NotasFrequencia": 495,
    "Footer_NotasFrequencia_1": 524,
    "Footer_NotasFrequencia_2": 69,
    "Footer_SucessoCadastro": 471,
    "Footer_TelaCadastro": 41,
    "Footer_TelaCadastro2": 313,
    "Footer_TelaCadastro3": 413,
    "Footer_TelaLogin": 452,
    "Footer_Turma": 432,
    "Footer_VisNotasFrequencia": 135,
    "FormDados": 273,
    "FormLogin": 8,
    "Gallery1": 320,
    "Gallery2": 481,
    "galleryTemplate1": 321,
    "galleryTemplate2": 482,
    "Header_Atividade": 201,
    "Header_Atividade_1": 179,
    "Header_Avisos": 375,
    "Header_Avisos_1": 354,
    "Header_Avisos_2": 112,
    "Header_Avisos_3": 156,
    "Header_Calendario": 335,
    "Header_CursoDisciplinas": 92,
    "Header_Home": 258,
    "Header_NotasFrequencia": 496,
    "Header_NotasFrequencia_1": 525,
    "Header_NotasFrequencia_2": 70,
    "Header_SucessoCadastro": 470,
    "Header_TelaCadastro1": 39,
    "Header_TelaCadastro2": 312,
    "Header_TelaCadastro3": 412,
    "Header_TelaLogin": 453,
    "Header_Turma": 433,
    "Header_VisNotasFrequencia": 136,
    "HourValue1": 298,
    "Icon1": 386,
    "Icon2": 480,
    "Icon2_1": 248,
    "Icon2_13": 359,
    "Icon2_14": 183,
    "Icon2_15": 75,
    "Icon2_16": 417,
    "Icon2_17": 475,
    "Icon2_18": 117,
    "Icon2_19": 317,
    "Icon2_2": 236,
    "Icon2_20": 339,
    "Icon2_21": 500,
    "Icon2_22": 45,
    "Icon2_23": 96,
    "Icon2_24": 140,
    "Icon2_25": 161,
    "Icon2_3": 241,
    "Icon2_4": 235,
    "Icon3": 210,
    "Icon3_1": 216,
    "Icon4": 205,
    "Icon5": 227,
    "Image1": 7,
    "Image1_1": 272,
    "Image1_3": 381,
    "Image12": 436,
    "Image12_1": 5,
    "Image12_16": 456,
    "Image12_17": 234,
    "Image12_19": 358,
    "Image12_2": 270,
    "Image12_20": 182,
    "Image12_21": 74,
    "Image12_22": 416,
    "Image12_23": 474,
    "Image12_24": 116,
    "Image12_25": 316,
    "Image12_26": 338,
    "Image12_27": 499,
    "Image12_28": 44,
    "Image12_29": 95,
    "Image12_30": 139,
    "Image12_31": 160,
    "Image12_8": 379,
    "Image13": 437,
    "Image16": 206,
    "Image21": 217,
    "Image22": 219,
    "Image23": 221,
    "Image24": 223,
    "Image25": 77,
    "Image25_1": 80,
    "Image25_2": 418,
    "Image25_3": 477,
    "Image25_4": 185,
    "Image25_5": 318,
    "Image25_6": 459,
    "Image25_7": 119,
    "Image25_9": 163,
    "Image3_1": 501,
    "Image3_2": 211,
    "Image3_3": 213,
    "Image3_4": 361,
    "Image3_5": 341,
    "Image3_6": 46,
    "Image3_7": 98,
    "Image3_8": 142,
    "Image5": 226,
    "Image6": 262,
    "Instagram": 447,
    "Instagram_1": 34,
    "Instagram_10": 86,
    "Instagram_11": 427,
    "Instagram_12": 490,
    "Instagram_13": 130,
    "Instagram_14": 329,
    "Instagram_15": 348,
    "Instagram_16": 519,
    "Instagram_17": 64,
    "Instagram_18": 106,
    "Instagram_19": 150,
    "Instagram_20": 172,
    "Instagram_3": 306,
    "Instagram_4": 405,
    "Instagram_5": 465,
    "Instagram_6": 253,
    "Instagram_8": 369,
    "Instagram_9": 194,
    "Já tem cadastro": 263,
    "Label1": 6,
    "Label1_1": 271,
    "Label1_10": 141,
    "Label1_11": 237,
    "Label1_12": 162,
    "Label1_15": 81,
    "Label1_16": 419,
    "Label1_17": 476,
    "Label1_18": 502,
    "Label1_19": 319,
    "Label1_20": 47,
    "Label1_21": 118,
    "Label1_22": 78,
    "Label1_23": 460,
    "Label1_4": 244,
    "Label1_5": 380,
    "Label1_6": 360,
    "Label1_7": 184,
    "Label1_8": 340,
    "Label1_9": 97,
    "Label10": 209,
    "Label10_1": 215,
    "Label12_1": 121,
    "Label13_1": 122,
    "Label14_1": 124,
    "Label15": 478,
    "Label15_1": 125,
    "Label17": 120,
    "Label18": 123,
    "Label19": 364,
    "Label19_1": 362,
    "Label19_2": 342,
    "Label19_3": 344,
    "Label19_4": 99,
    "Label19_5": 101,
    "Label19_6": 143,
    "Label19_7": 145,
    "Label2": 384,
    "Label20": 363,
    "Label20_1": 343,
    "Label20_2": 100,
    "Label20_3": 144,
    "Label21": 365,
    "Label21_1": 102,
    "Label21_2": 146,
    "Label22": 190,
    "Label22_1": 168,
    "Label23": 189,
    "Label23_1": 167,
    "Label24": 188,
    "Label24_1": 166,
    "Label25": 186,
    "Label25_1": 164,
    "Label26": 420,
    "Label27": 421,
    "Label28": 422,
    "Label3": 457,
    "Label4": 382,
    "Label5": 207,
    "Label6": 387,
    "Label6_1": 388,
    "Label6_2": 391,
    "Label6_3": 393,
    "Label6_4": 394,
    "Label7": 76,
    "Label8_2": 247,
    "Label8_3": 240,
    "Label8_4": 504,
    "Label8_5": 508,
    "Label8_6": 49,
    "Label8_7": 53,
    "Label9_10": 242,
    "Label9_11": 165,
    "Label9_2": 249,
    "Label9_3": 246,
    "Label9_4": 239,
    "Label9_5": 187,
    "Label9_6": 505,
    "Label9_7": 509,
    "Label9_8": 54,
    "Label9_9": 50,
    "LabelNomeCurso": 208,
    "lbErroConfirmaEmail": 30,
    "lbErroEntradaEmail": 29,
    "Linkedin": 448,
    "Linkedin_1": 35,
    "Linkedin_10": 87,
    "Linkedin_11": 428,
    "Linkedin_12": 491,
    "Linkedin_13": 131,
    "Linkedin_14": 330,
    "Linkedin_15": 349,
    "Linkedin_16": 520,
    "Linkedin_17": 65,
    "Linkedin_18": 107,
    "Linkedin_19": 151,
    "Linkedin_20": 173,
    "Linkedin_3": 307,
    "Linkedin_4": 406,
    "Linkedin_5": 466,
    "Linkedin_6": 254,
    "Linkedin_8": 370,
    "Linkedin_9": 195,
    "lstCursos": 79,
    "lstCursos_1": 423,
    "lstCursos_2": 461,
    "lstDisciplinas": 82,
    "Meu perfil": 231,
    "MinuteValue1": 300,
    "MuralAvisos1": 497,
    "MuralAvisos2": 42,
    "Não tem cadastro": 265,
    "NextArrow4": 323,
    "NextArrow5": 485,
    "Nome Completo_DataCard1": 274,
    "Nome Social_DataCard1": 279,
    "NotasFrequencia": 472,
    "Pag<_1": 511,
    "Pag<_2": 56,
    "Pag>_1": 513,
    "Pag>_2": 57,
    "Pag1_1": 512,
    "Pag3_1": 514,
    "Pag3_2": 59,
    "Pag4_1": 515,
    "Pag4_2": 60,
    "Paginacao_1": 526,
    "Paginacao_2": 71,
    "PaginaInativa": 72,
    "Perfil": 230,
    "Politica de privacidade": 399,
    "Politica Privacidade": 410,
    "Rectangle1_10": 238,
    "Rectangle1_2": 126,
    "Rectangle1_5": 245,
    "Rectangle1_6": 503,
    "Rectangle1_7": 48,
    "Rectangle1_8": 507,
    "Rectangle1_9": 52,
    "Rectangle2": 204,
    "Rectangle3": 435,
    "Rectangle3_1": 4,
    "Rectangle3_14": 203,
    "Rectangle3_15": 225,
    "Rectangle3_16": 378,
    "Rectangle3_17": 403,
    "Rectangle3_2": 445,
    "Rectangle3_3": 269,
    "Rectangle3_32": 455,
    "Rectangle3_33": 463,
    "Rectangle3_34": 233,
    "Rectangle3_35": 251,
    "Rectangle3_38": 367,
    "Rectangle3_39": 357,
    "Rectangle3_4": 32,
    "Rectangle3_40": 192,
    "Rectangle3_41": 181,
    "Rectangle3_42": 84,
    "Rectangle3_43": 73,
    "Rectangle3_44": 425,
    "Rectangle3_45": 415,
    "Rectangle3_46": 488,
    "Rectangle3_47": 473,
    "Rectangle3_48": 128,
    "Rectangle3_49": 115,
    "Rectangle3_5": 304,
    "Rectangle3_50": 327,
    "Rectangle3_51": 315,
    "Rectangle3_52": 337,
    "Rectangle3_53": 346,
    "Rectangle3_54": 498,
    "Rectangle3_55": 517,
    "Rectangle3_56": 43,
    "Rectangle3_57": 62,
    "Rectangle3_58": 94,
    "Rectangle3_59": 104,
    "Rectangle3_60": 138,
    "Rectangle3_61": 148,
    "Rectangle3_62": 159,
    "Rectangle3_63": 170,
    "Senha": 440,
    "Senha_DataCard1": 19,
    "SenhaIncorreta": 442,
    "Separator1": 299,
    "Separator5": 325,
    "Separator6": 487,
    "Sexo_DataCard1": 289,
    "StarVisible1": 295,
    "StarVisible2": 15,
    "StarVisible3": 25,
    "StarVisible4": 20,
    "StarVisible5": 10,
    "StarVisible6": 275,
    "StarVisible7": 280,
    "StarVisible8": 285,
    "StarVisible9": 290,
    "Subtitle3": 484,
    "Subtitle4": 324,
    "SucessoCadastro": 454,
    "TelaAcesso": 261,
    "TelaCadastro1": 3,
    "TelaCadastro2": 268,
    "TelaCadastro3": 377,
    "TelaLogin": 434,
    "TelaMenu": 202,
    "TextInput1": 383,
    "TextInputEmail": 439,
    "TextInputNotasFaltas": 479,
    "TextInputSenha": 441,
    "Timetable": 400,
    "Title4": 322,
    "Title5": 483,
    "Titulo_Atividade": 200,
    "Titulo_Atividade_1": 178,
    "Titulo_Avisos": 376,
    "Titulo_Avisos_1": 355,
    "Titulo_Avisos_2": 113,
    "Titulo_Avisos_3": 157,
    "Titulo_TelaCadastro1": 40,
    "Titulo_TelaCadastro2": 311,
    "Titulo_TelaCadastro3": 411,
    "Todos os direitos reservados": 267,
    "Todos os direitos reservados_10": 373,
    "Todos os direitos reservados_11": 198,
    "Todos os direitos reservados_12": 90,
    "Todos os direitos reservados_13": 431,
    "Todos os direitos reservados_14": 494,
    "Todos os direitos reservados_15": 134,
    "Todos os direitos reservados_16": 333,
    "Todos os direitos reservados_17": 352,
    "Todos os direitos reservados_18": 523,
    "Todos os direitos reservados_19": 68,
    "Todos os direitos reservados_2": 451,
    "Todos os direitos reservados_20": 110,
    "Todos os direitos reservados_21": 154,
    "Todos os direitos reservados_22": 176,
    "Todos os direitos reservados_3": 38,
    "Todos os direitos reservados_5": 310,
    "Todos os direitos reservados_6": 409,
    "Todos os direitos reservados_7": 469,
    "Todos os direitos reservados_8": 257,
    "TurmaInativa": 414,
    "Twitter": 450,
    "Twitter_1": 37,
    "Twitter_10": 89,
    "Twitter_11": 430,
    "Twitter_12": 493,
    "Twitter_13": 133,
    "Twitter_14": 332,
    "Twitter_15": 351,
    "Twitter_16": 522,
    "Twitter_17": 67,
    "Twitter_18": 109,
    "Twitter_19": 153,
    "Twitter_20": 175,
    "Twitter_3": 309,
    "Twitter_4": 408,
    "Twitter_5": 468,
    "Twitter_6": 256,
    "Twitter_8": 372,
    "Twitter_9": 197,
    "TxtCep": 385,
    "TxtCep_1": 389,
    "TxtCep_2": 392,
    "TxtCep_3": 390,
    "TxtCep_4": 395,
    "TxtCep_5": 396,
    "UltimasAtividades": 260,
    "Visualizar Notas e Frequência": 114,
    "Youtube": 449,
    "Youtube_1": 36,
    "Youtube_10": 88,
    "Youtube_11": 429,
    "Youtube_12": 492,
    "Youtube_13": 132,
    "Youtube_14": 331,
    "Youtube_15": 350,
    "Youtube_16": 521,
    "Youtube_17": 66,
    "Youtube_18": 108,
    "Youtube_19": 152,
    "Youtube_20": 174,
    "Youtube_3": 308,
    "Youtube_4": 407,
    "Youtube_5": 467,
    "Youtube_6": 255,
    "Youtube_8": 371,
    "Youtube_9": 196
  },
  "FunctionParamsInvariantScripts": {},
  "FunctionParamsInvariantScriptsOnInstances": {},
  "HeaderLastSavedDateTimeUTC": "03/11/2023 19:43:52",
  "IsLegacyComponentAllowGlobalScopeCase": false,
  "LocalConnectionIDReferences": {
    "011faafa-c34d-46b3-87be-7ccdd485d9cb": "\"/providers/microsoft.powerapps/apis/shared_sharepointonline/connections/e9911849802646e781efbefd2f311fa9\"",
    "50471254-8922-4980-9b2b-f48fb005d5a9": "\"/providers/microsoft.powerapps/apis/shared_logicflows/connections/a51f0f040a8c4391acf88880ace98876-61c895ebdf0a9d83\"",
    "68fdde3e-59e6-4b66-bd28-f6116d9e01ea": "\"/providers/microsoft.powerapps/apis/shared_sharepointonline/connections/ac94d24582b6452f8d790728206f90e8\""
  },
  "LocalDatabaseReferencesAsEmpty": false,
  "LocalResourceFileNames": {
    "10": "272c64ae-f126-4499-8722-3304d0d850d6.png",
    "18": "2befdcbc-41e2-4812-b049-fc2c81e018b7.png",
    "19 1": "58b83cfb-5e7f-4a58-86ca-dfeef9b282c3.png",
    "2": "5a8b0286-e92b-4903-bac5-c2103a384a20.png",
    "2_1": "140b3580-dd46-441f-ae91-ee1f2e7b5907.png",
    "20": "8c8b29e7-21d4-4179-84e0-ea3840ea1043.png",
    "24": "498cd539-7246-4918-b13c-6d72a2dac2e3.png",
    "25": "c5180adc-19a5-4a9c-8b42-732de98f1175.png",
    "26": "02d55896-fa71-4e16-920a-9bcbeefab880.png",
    "27": "b4968b17-ffe5-43f9-b194-c073e426a465.png",
    "28": "bed9fe89-22f9-4f89-92bd-8ae7097888cf.png",
    "29": "5d350645-a7f5-4b98-906c-56d304453a0d.png",
    "32": "25b62121-fa79-4bbe-9771-b8749b6862d1.png",
    "7": "b5e2a8c4-4d47-4c46-bb65-d821add64b0e.png",
    "bg-btn": "0df5e589-e17c-4a11-b560-88a64c03b3e1.png",
    "bg-btn_1": "9aa4c843-e4a5-4d04-b2ec-a4655696e7d8.png",
    "Ellipse 1": "5ac0995f-6846-4dbc-b347-56db6d374852.png",
    "EnsinoSuperior": "f56fbdca-6be8-4e56-905a-177264442da6.png",
    "Esqueci a senha _ Suporte login": "b9023b64-3584-49eb-89bb-22c61c414160.png",
    "Footer": "c03a0313-1778-4a44-9438-269a28e6b638.png",
    "FooterIcones": "cc4f2ed9-4225-49f3-9ece-7524febc0ee1.png",
    "Group 3": "13c6bef3-45ca-44c0-b369-a463be3a309d.png",
    "Group 3_1": "aab301e2-2800-44f8-b222-58440cf8fd3d.png",
    "Header liso": "3585d97f-d130-4acb-b027-7b9dcdbb3e9e.png",
    "icon1": "9d506386-b319-4af0-a4f9-98fa05e3be07.jpg",
    "icons8-facebook-90": "33e23749-7bbd-4530-b6bc-9b64e752a46d.png",
    "icons8-instagram-128": "4800a3eb-2b8c-4e6c-9f51-12e318aa22ef.png",
    "icons8-linkedin-128": "add7fe31-5bed-4a25-b6bf-1317ffc45d60.png",
    "icons8-twitter-squared-64": "7bdef63b-d165-4739-93db-985741f1cefb.png",
    "icons8-youtube-squared-128": "5ce6c74c-7904-44b6-840e-670bc7c3d26d.png",
    "Já tem cadastro_": "3257cea4-819a-4eb4-8c5f-38ccc80d307f.png",
    "meuperfil": "5a2a6c43-4dbb-4a6e-ba25-5f9cd762fbc6.png",
    "Não tem cadastro_": "2aed7137-4b43-4654-a817-67bd300a6a1b.png",
    "NATAL 2022": "837c4769-3204-413c-9c22-0382199f1d30.png",
    "NATAL 2022_1": "2b2d9078-77ca-45a2-a31b-49f302c5d437.png",
    "partebaixo": "227cf407-8a63-460e-93bf-36c7706da5e4.jpg",
    "privacidade": "d8cdc662-3752-4a74-9f3b-909a8177254e.jpg",
    "Rectangle 26": "15db3776-5d81-409a-b5dd-99aac5994832.png",
    "Rectangle 27": "42ee8732-a2bf-4697-9a06-7af6432ff0bf.png",
    "Section 3": "93fbc403-e275-411e-9cc3-39fe942238af.png",
    "Todos os Direitos Reservados - 2022": "b044b0f5-0b4b-4bc5-be07-b4fe9e4299ef.png"
  },
  "LocalResourceRootPaths": {
    "10": "https://docserverpwaprodsbr.blob.core.windows.net/a81e6353-29f4-4580-b3f7-f090d3db6ec0-1/resource/Assets0Images0272c64ae-f126-4499-8722-3304d0d850d6.png?sv=2018-03-28&sr=b&sig=7axjQgrHH2cP%2FzxQp4%2FM56GK3sMv6klaB58ZLMbKvHQ%3D&spr=https&se=2023-03-12T19%3A57%3A59Z&sp=r",
    "18": "https://docserverpwaprodsbr.blob.core.windows.net/a81e6353-29f4-4580-b3f7-f090d3db6ec0-1/resource/Assets0Images02befdcbc-41e2-4812-b049-fc2c81e018b7.png?sv=2018-03-28&sr=b&sig=du%2BDUqzqu3ftkw0ey%2BOoLOrNf6fxpYoj7iPAGkB%2BBNw%3D&spr=https&se=2023-03-12T19%3A57%3A59Z&sp=r",
    "19 1": "https://docserverpwaprodsbr.blob.core.windows.net/a81e6353-29f4-4580-b3f7-f090d3db6ec0-1/resource/Assets0Images058b83cfb-5e7f-4a58-86ca-dfeef9b282c3.png?sv=2018-03-28&sr=b&sig=vRslt1Jp2IH78aU8VYtppG3rSL0Um9x3GHJ8q%2FiMV%2FY%3D&spr=https&se=2023-03-12T19%3A57%3A59Z&sp=r",
    "2": "https://docserverpwaprodsbr.blob.core.windows.net/a81e6353-29f4-4580-b3f7-f090d3db6ec0-1/resource/Assets0Images05a8b0286-e92b-4903-bac5-c2103a384a20.png?sv=2018-03-28&sr=b&sig=fK6TZVz92mxze51pq%2FOP0NHhrYJ9Oo5E8fHthd4JoiQ%3D&spr=https&se=2023-03-12T19%3A57%3A59Z&sp=r",
    "2_1": "https://docserverpwaprodsbr.blob.core.windows.net/a81e6353-29f4-4580-b3f7-f090d3db6ec0-1/resource/Assets0Images0140b3580-dd46-441f-ae91-ee1f2e7b5907.png?sv=2018-03-28&sr=b&sig=4TpWEVAe2QH6iV30BluQOTwAEBUw%2FO87R%2FJaSKo1rzo%3D&spr=https&se=2023-03-12T19%3A57%3A59Z&sp=r",
    "20": "https://docserverpwaprodsbr.blob.core.windows.net/a81e6353-29f4-4580-b3f7-f090d3db6ec0-1/resource/Assets0Images08c8b29e7-21d4-4179-84e0-ea3840ea1043.png?sv=2018-03-28&sr=b&sig=OtRgyefZAWdPpBp7T5m4sdU2amVr8f6i9S%2BzimKOM10%3D&spr=https&se=2023-03-12T19%3A57%3A59Z&sp=r",
    "24": "https://docserverpwaprodsbr.blob.core.windows.net/a81e6353-29f4-4580-b3f7-f090d3db6ec0-1/resource/Assets0Images0498cd539-7246-4918-b13c-6d72a2dac2e3.png?sv=2018-03-28&sr=b&sig=F10BXD8J7JjnXhNo4%2BGVmrtuDGzwfnpBWOQ%2BtWWlziY%3D&spr=https&se=2023-03-12T19%3A57%3A59Z&sp=r",
    "25": "https://docserverpwaprodsbr.blob.core.windows.net/a81e6353-29f4-4580-b3f7-f090d3db6ec0-1/resource/Assets0Images0c5180adc-19a5-4a9c-8b42-732de98f1175.png?sv=2018-03-28&sr=b&sig=wP3P4TuvisF2XASEZCAfu623zwigZFu%2Fa4PnysxHr2Q%3D&spr=https&se=2023-03-12T19%3A57%3A59Z&sp=r",
    "26": "https://docserverpwaprodsbr.blob.core.windows.net/a81e6353-29f4-4580-b3f7-f090d3db6ec0-1/resource/Assets0Images002d55896-fa71-4e16-920a-9bcbeefab880.png?sv=2018-03-28&sr=b&sig=oY4JtjpW%2F6Np7E%2ByBcz79geFTekFrfv18ZByNkySTHU%3D&spr=https&se=2023-03-12T19%3A57%3A59Z&sp=r",
    "27": "https://docserverpwaprodsbr.blob.core.windows.net/a81e6353-29f4-4580-b3f7-f090d3db6ec0-1/resource/Assets0Images0b4968b17-ffe5-43f9-b194-c073e426a465.png?sv=2018-03-28&sr=b&sig=vmMR9nyDz1WgxtbSY2FDMTeazxtgX7tkv7NwNNJakBU%3D&spr=https&se=2023-03-12T19%3A57%3A59Z&sp=r",
    "28": "https://docserverpwaprodsbr.blob.core.windows.net/a81e6353-29f4-4580-b3f7-f090d3db6ec0-1/resource/Assets0Images0bed9fe89-22f9-4f89-92bd-8ae7097888cf.png?sv=2018-03-28&sr=b&sig=Iw7Qefnza366y74DdOlDR0%2FAKKQ0gWduv%2FJWxUOGiEA%3D&spr=https&se=2023-03-12T19%3A57%3A59Z&sp=r",
    "29": "https://docserverpwaprodsbr.blob.core.windows.net/a81e6353-29f4-4580-b3f7-f090d3db6ec0-1/resource/Assets0Images05d350645-a7f5-4b98-906c-56d304453a0d.png?sv=2018-03-28&sr=b&sig=cmyxPljE8a1JpFcCCNnRIiS1DmGwde%2FMAwpIvZJfti0%3D&spr=https&se=2023-03-12T19%3A57%3A59Z&sp=r",
    "32": "https://docserverpwaprodsbr.blob.core.windows.net/a81e6353-29f4-4580-b3f7-f090d3db6ec0-1/resource/Assets0Images025b62121-fa79-4bbe-9771-b8749b6862d1.png?sv=2018-03-28&sr=b&sig=pF%2FL0MgvhN8AA5Wfaj1IDgNoZEAHY4liQ7Y53Q0ZlEs%3D&spr=https&se=2023-03-12T19%3A57%3A59Z&sp=r",
    "7": "https://docserverpwaprodsbr.blob.core.windows.net/a81e6353-29f4-4580-b3f7-f090d3db6ec0-1/resource/Assets0Images0b5e2a8c4-4d47-4c46-bb65-d821add64b0e.png?sv=2018-03-28&sr=b&sig=aZTzyT%2B%2BOCDa28Asc0%2FqQfkecKkZmwoyoLHzzpy2L9w%3D&spr=https&se=2023-03-12T19%3A57%3A59Z&sp=r",
    "bg-btn": "https://docserverpwaprodsbr.blob.core.windows.net/a81e6353-29f4-4580-b3f7-f090d3db6ec0-1/resource/Assets0Images00df5e589-e17c-4a11-b560-88a64c03b3e1.png?sv=2018-03-28&sr=b&sig=RdZIw%2FMcVCNQy6DD47TdTa4yoHb9AH8eBUFnLnHDV9I%3D&spr=https&se=2023-03-12T19%3A57%3A59Z&sp=r",
    "bg-btn_1": "https://docserverpwaprodsbr.blob.core.windows.net/a81e6353-29f4-4580-b3f7-f090d3db6ec0-1/resource/Assets0Images09aa4c843-e4a5-4d04-b2ec-a4655696e7d8.png?sv=2018-03-28&sr=b&sig=My%2FZjZwrAESgZnl1xPdG%2FB2I0%2FRgmY%2B%2Bl1%2FaU8Q5uqo%3D&spr=https&se=2023-03-12T19%3A57%3A59Z&sp=r",
    "Ellipse 1": "https://docserverpwaprodsbr.blob.core.windows.net/a81e6353-29f4-4580-b3f7-f090d3db6ec0-1/resource/Assets0Images05ac0995f-6846-4dbc-b347-56db6d374852.png?sv=2018-03-28&sr=b&sig=3mQk0tdckZ9AWEqlGJpZTIJ9yE1P6ndGkXi20%2BdH8Yw%3D&spr=https&se=2023-03-12T19%3A57%3A59Z&sp=r",
    "EnsinoSuperior": "https://docserverpwaprodsbr.blob.core.windows.net/a81e6353-29f4-4580-b3f7-f090d3db6ec0-1/resource/Assets0Images0f56fbdca-6be8-4e56-905a-177264442da6.png?sv=2018-03-28&sr=b&sig=m%2FzsJ2TwKpV73euEmkeR2sbKjGmFenNHcRjDiDcrvzU%3D&spr=https&se=2023-03-12T19%3A57%3A59Z&sp=r",
    "Esqueci a senha _ Suporte login": "https://docserverpwaprodsbr.blob.core.windows.net/a81e6353-29f4-4580-b3f7-f090d3db6ec0-1/resource/Assets0Images0b9023b64-3584-49eb-89bb-22c61c414160.png?sv=2018-03-28&sr=b&sig=NKlqXHvL0n7EQ0CKa8KN%2F11AFd%2FCdrZHDDqTfOA8fEw%3D&spr=https&se=2023-03-12T19%3A57%3A59Z&sp=r",
    "Footer": "https://docserverpwaprodsbr.blob.core.windows.net/a81e6353-29f4-4580-b3f7-f090d3db6ec0-1/resource/Assets0Images0c03a0313-1778-4a44-9438-269a28e6b638.png?sv=2018-03-28&sr=b&sig=B%2BfRBO5PjF2fBnI02MpgBWXkgWOYGTlDFiUKkuXNfnc%3D&spr=https&se=2023-03-12T19%3A57%3A59Z&sp=r",
    "FooterIcones": "https://docserverpwaprodsbr.blob.core.windows.net/a81e6353-29f4-4580-b3f7-f090d3db6ec0-1/resource/Assets0Images0cc4f2ed9-4225-49f3-9ece-7524febc0ee1.png?sv=2018-03-28&sr=b&sig=WKtOhhKlvvehbk8pJgDiRvDUsoJXfHUMNkPbmPudKdA%3D&spr=https&se=2023-03-12T19%3A57%3A59Z&sp=r",
    "Group 3": "https://docserverpwaprodsbr.blob.core.windows.net/a81e6353-29f4-4580-b3f7-f090d3db6ec0-1/resource/Assets0Images013c6bef3-45ca-44c0-b369-a463be3a309d.png?sv=2018-03-28&sr=b&sig=b%2BLPBugqms7cIXYBHXwnn%2B1Ac23FEVF8vfV66soQ87c%3D&spr=https&se=2023-03-12T19%3A57%3A59Z&sp=r",
    "Group 3_1": "https://docserverpwaprodsbr.blob.core.windows.net/a81e6353-29f4-4580-b3f7-f090d3db6ec0-1/resource/Assets0Images0aab301e2-2800-44f8-b222-58440cf8fd3d.png?sv=2018-03-28&sr=b&sig=UiQkwERJyZdY1w1eHziUf0URwxDWjNKdpqdyL8in188%3D&spr=https&se=2023-03-12T19%3A57%3A59Z&sp=r",
    "Header liso": "https://docserverpwaprodsbr.blob.core.windows.net/a81e6353-29f4-4580-b3f7-f090d3db6ec0-1/resource/Assets0Images03585d97f-d130-4acb-b027-7b9dcdbb3e9e.png?sv=2018-03-28&sr=b&sig=GQ1sXlF6K5qrKaCcFxvnYy3OQMVhUG8jhgcMQ4vcJd8%3D&spr=https&se=2023-03-12T19%3A57%3A59Z&sp=r",
    "icon1": "https://docserverpwaprodsbr.blob.core.windows.net/a81e6353-29f4-4580-b3f7-f090d3db6ec0-1/resource/Assets0Images09d506386-b319-4af0-a4f9-98fa05e3be07.jpg?sv=2018-03-28&sr=b&sig=6mOoyHjiyYIw3soMxjs888xv5jdgiubybd5EBHg4%2FPE%3D&spr=https&se=2023-03-12T19%3A57%3A59Z&sp=r",
    "icons8-facebook-90": "https://docserverpwaprodsbr.blob.core.windows.net/a81e6353-29f4-4580-b3f7-f090d3db6ec0-1/resource/Assets0Images033e23749-7bbd-4530-b6bc-9b64e752a46d.png?sv=2018-03-28&sr=b&sig=X%2Bms%2FdrDTqR2vOHdmkbDQb8Fo1e2fuC%2FRhSQeNwgLz8%3D&spr=https&se=2023-03-12T19%3A57%3A59Z&sp=r",
    "icons8-instagram-128": "https://docserverpwaprodsbr.blob.core.windows.net/a81e6353-29f4-4580-b3f7-f090d3db6ec0-1/resource/Assets0Images04800a3eb-2b8c-4e6c-9f51-12e318aa22ef.png?sv=2018-03-28&sr=b&sig=3BhOaHD6l5t0WIffYj9qzBGfs9ChXq9%2Fq7Xi6dzHGzE%3D&spr=https&se=2023-03-12T19%3A57%3A59Z&sp=r",
    "icons8-linkedin-128": "https://docserverpwaprodsbr.blob.core.windows.net/a81e6353-29f4-4580-b3f7-f090d3db6ec0-1/resource/Assets0Images0add7fe31-5bed-4a25-b6bf-1317ffc45d60.png?sv=2018-03-28&sr=b&sig=aPjux2ZbMcLXhlS4AFOtQ1d5PPRHoPEE0pz1GKIepBs%3D&spr=https&se=2023-03-12T19%3A57%3A59Z&sp=r",
    "icons8-twitter-squared-64": "https://docserverpwaprodsbr.blob.core.windows.net/a81e6353-29f4-4580-b3f7-f090d3db6ec0-1/resource/Assets0Images07bdef63b-d165-4739-93db-985741f1cefb.png?sv=2018-03-28&sr=b&sig=DEvIBo%2FekY1GmekapBASHC7iLbG0egFdyzRRpX99YZg%3D&spr=https&se=2023-03-12T19%3A57%3A59Z&sp=r",
    "icons8-youtube-squared-128": "https://docserverpwaprodsbr.blob.core.windows.net/a81e6353-29f4-4580-b3f7-f090d3db6ec0-1/resource/Assets0Images05ce6c74c-7904-44b6-840e-670bc7c3d26d.png?sv=2018-03-28&sr=b&sig=sD2ZpvfWVC1U0X4FJKmfNLNdGobDusdRAJmtooE37ZY%3D&spr=https&se=2023-03-12T19%3A57%3A59Z&sp=r",
    "Já tem cadastro_": "https://docserverpwaprodsbr.blob.core.windows.net/a81e6353-29f4-4580-b3f7-f090d3db6ec0-1/resource/Assets0Images03257cea4-819a-4eb4-8c5f-38ccc80d307f.png?sv=2018-03-28&sr=b&sig=QH7JjiY5iNOvIE0KUZQ%2FTGayW1TyXPKCUNhHI2avTBY%3D&spr=https&se=2023-03-12T19%3A57%3A59Z&sp=r",
    "meuperfil": "https://docserverpwaprodsbr.blob.core.windows.net/a81e6353-29f4-4580-b3f7-f090d3db6ec0-1/resource/Assets0Images05a2a6c43-4dbb-4a6e-ba25-5f9cd762fbc6.png?sv=2018-03-28&sr=b&sig=hNqPjGpp%2F7y%2F7bqn4nOIkO6N9idGrRJbZJm31oiibus%3D&spr=https&se=2023-03-12T19%3A57%3A59Z&sp=r",
    "Não tem cadastro_": "https://docserverpwaprodsbr.blob.core.windows.net/a81e6353-29f4-4580-b3f7-f090d3db6ec0-1/resource/Assets0Images02aed7137-4b43-4654-a817-67bd300a6a1b.png?sv=2018-03-28&sr=b&sig=WXCoEFXBTYof3jxrocM9k2CGjqUa2lWGilpblf89I4U%3D&spr=https&se=2023-03-12T19%3A57%3A59Z&sp=r",
    "NATAL 2022": "https://docserverpwaprodsbr.blob.core.windows.net/a81e6353-29f4-4580-b3f7-f090d3db6ec0-1/resource/Assets0Images0837c4769-3204-413c-9c22-0382199f1d30.png?sv=2018-03-28&sr=b&sig=Eka64WE5D4fEwYB%2BC4e0kE1FrKgcn44zU%2FByaitedFM%3D&spr=https&se=2023-03-12T19%3A57%3A59Z&sp=r",
    "NATAL 2022_1": "https://docserverpwaprodsbr.blob.core.windows.net/a81e6353-29f4-4580-b3f7-f090d3db6ec0-1/resource/Assets0Images02b2d9078-77ca-45a2-a31b-49f302c5d437.png?sv=2018-03-28&sr=b&sig=F8UDxDDL3dTLX6TX1Ms2pxheKm%2F%2FW3F5DRlxU6wv6JY%3D&spr=https&se=2023-03-12T19%3A57%3A59Z&sp=r",
    "partebaixo": "https://docserverpwaprodsbr.blob.core.windows.net/a81e6353-29f4-4580-b3f7-f090d3db6ec0-1/resource/Assets0Images0227cf407-8a63-460e-93bf-36c7706da5e4.jpg?sv=2018-03-28&sr=b&sig=4yYK1HRWLaixiR9%2BkSxQT1P94iUco0I60iTG685O6sE%3D&spr=https&se=2023-03-12T19%3A57%3A59Z&sp=r",
    "privacidade": "https://docserverpwaprodsbr.blob.core.windows.net/a81e6353-29f4-4580-b3f7-f090d3db6ec0-1/resource/Assets0Images0d8cdc662-3752-4a74-9f3b-909a8177254e.jpg?sv=2018-03-28&sr=b&sig=KKNgde6PfVeweb8Mjm8XX7ktqzOjJI2jErdK6ZOV6fM%3D&spr=https&se=2023-03-12T19%3A57%3A59Z&sp=r",
    "Rectangle 26": "https://docserverpwaprodsbr.blob.core.windows.net/a81e6353-29f4-4580-b3f7-f090d3db6ec0-1/resource/Assets0Images015db3776-5d81-409a-b5dd-99aac5994832.png?sv=2018-03-28&sr=b&sig=4DOYQBwE9CY1AQTBj%2BlJCnT%2BoB8EwW7Q48G7KosBnVk%3D&spr=https&se=2023-03-12T19%3A57%3A59Z&sp=r",
    "Rectangle 27": "https://docserverpwaprodsbr.blob.core.windows.net/a81e6353-29f4-4580-b3f7-f090d3db6ec0-1/resource/Assets0Images042ee8732-a2bf-4697-9a06-7af6432ff0bf.png?sv=2018-03-28&sr=b&sig=tUSrfXg2%2FxlHtQ2UFDbLjduHDSGUA9%2BbqGI7cwHoDb4%3D&spr=https&se=2023-03-12T19%3A57%3A59Z&sp=r",
    "Section 3": "https://docserverpwaprodsbr.blob.core.windows.net/a81e6353-29f4-4580-b3f7-f090d3db6ec0-1/resource/Assets0Images093fbc403-e275-411e-9cc3-39fe942238af.png?sv=2018-03-28&sr=b&sig=0nL%2BftatFAuYgLlWVYyEBdi1xR2rdbcCNvZy9gOtwB4%3D&spr=https&se=2023-03-12T19%3A57%3A59Z&sp=r",
    "Todos os Direitos Reservados - 2022": "https://docserverpwaprodsbr.blob.core.windows.net/a81e6353-29f4-4580-b3f7-f090d3db6ec0-1/resource/Assets0Images0b044b0f5-0b4b-4bc5-be07-b4fe9e4299ef.png?sv=2018-03-28&sr=b&sig=qNm4evhikNkLgPGSfiR9g6maJCygl9p18TG72OsYZ6Q%3D&spr=https&se=2023-03-12T19%3A57%3A59Z&sp=r"
  },
  "OldLogoFileName": "4zp03d1f.jpg",
  "OrderComponentMetadata": {},
  "OrderComponentTemplate": {},
  "OrderDataSource": {
    "Calendário TimeTable": 14,
    "CollectTeste": 16,
    "ComboBoxSample": 10,
    "ConsultaCep": 0,
    "CustomGallerySample": 8,
    "Dados Aluno": 12,
    "Dados Aluno\\cr65a_dadosaluno_cr65a_sexo": 3,
    "Dados Aluno\\cr65a_dadosaluno_statecode": 4,
    "Dados Aluno\\cr65a_dadosaluno_statuscode": 5,
    "Dados Aluno\\default.cds_cr65a_dadosaluno_views": 7,
    "DropDownSample": 9,
    "Login": 11,
    "Login\\cr65a_login_statecode": 1,
    "Login\\cr65a_login_statuscode": 2,
    "Login\\default.cds_cr65a_login_views": 6,
    "Notas e Faltas": 15,
    "RadioSample": 13
  },
  "OrderGroupControls": {
    "Ferramentas": {
      "Button3_3": 3,
      "Button3_4": 2,
      "Button3_5": 1,
      "Button3_6": 0,
      "Icon3_1": 4,
      "Image21": 9,
      "Image22": 8,
      "Image23": 7,
      "Image24": 6,
      "Label10_1": 5
    },
    "Footer_Atividade": {
      "Facebook_9": 5,
      "Instagram_9": 4,
      "Linkedin_9": 3,
      "Rectangle3_40": 0,
      "Todos os direitos reservados_11": 6,
      "Twitter_9": 1,
      "Youtube_9": 2
    },
    "Footer_Atividade_1": {
      "Facebook_20": 5,
      "Instagram_20": 4,
      "Linkedin_20": 3,
      "Rectangle3_63": 0,
      "Todos os direitos reservados_22": 6,
      "Twitter_20": 1,
      "Youtube_20": 2
    },
    "Footer_Avisos": {
      "Facebook_8": 5,
      "Instagram_8": 4,
      "Linkedin_8": 3,
      "Rectangle3_38": 0,
      "Todos os direitos reservados_10": 6,
      "Twitter_8": 1,
      "Youtube_8": 2
    },
    "Footer_Avisos_1": {
      "Facebook_15": 5,
      "Instagram_15": 4,
      "Linkedin_15": 3,
      "Rectangle3_53": 0,
      "Todos os direitos reservados_17": 6,
      "Twitter_15": 1,
      "Youtube_15": 2
    },
    "Footer_Avisos_2": {
      "Facebook_18": 5,
      "Instagram_18": 4,
      "Linkedin_18": 3,
      "Rectangle3_59": 0,
      "Todos os direitos reservados_20": 6,
      "Twitter_18": 1,
      "Youtube_18": 2
    },
    "Footer_Avisos_3": {
      "Facebook_19": 5,
      "Instagram_19": 4,
      "Linkedin_19": 3,
      "Rectangle3_61": 0,
      "Todos os direitos reservados_21": 6,
      "Twitter_19": 1,
      "Youtube_19": 2
    },
    "Footer_Calendario": {
      "Facebook_14": 5,
      "Instagram_14": 4,
      "Linkedin_14": 3,
      "Rectangle3_50": 0,
      "Todos os direitos reservados_16": 6,
      "Twitter_14": 1,
      "Youtube_14": 2
    },
    "Footer_CursoDisciplinas": {
      "Facebook_10": 5,
      "Instagram_10": 4,
      "Linkedin_10": 3,
      "Rectangle3_42": 0,
      "Todos os direitos reservados_12": 6,
      "Twitter_10": 1,
      "Youtube_10": 2
    },
    "Footer_Home": {
      "Facebook_6": 5,
      "Instagram_6": 4,
      "Linkedin_6": 3,
      "Rectangle3_35": 0,
      "Todos os direitos reservados_8": 6,
      "Twitter_6": 1,
      "Youtube_6": 2
    },
    "Footer_NotasFrequencia": {
      "Facebook_12": 5,
      "Instagram_12": 4,
      "Linkedin_12": 3,
      "Rectangle3_46": 0,
      "Todos os direitos reservados_14": 6,
      "Twitter_12": 1,
      "Youtube_12": 2
    },
    "Footer_NotasFrequencia_1": {
      "Facebook_16": 5,
      "Instagram_16": 4,
      "Linkedin_16": 3,
      "Rectangle3_55": 0,
      "Todos os direitos reservados_18": 6,
      "Twitter_16": 1,
      "Youtube_16": 2
    },
    "Footer_NotasFrequencia_2": {
      "Facebook_17": 5,
      "Instagram_17": 4,
      "Linkedin_17": 3,
      "Rectangle3_57": 0,
      "Todos os direitos reservados_19": 6,
      "Twitter_17": 1,
      "Youtube_17": 2
    },
    "Footer_SucessoCadastro": {
      "Facebook_5": 5,
      "Instagram_5": 4,
      "Linkedin_5": 3,
      "Rectangle3_33": 0,
      "Todos os direitos reservados_7": 6,
      "Twitter_5": 1,
      "Youtube_5": 2
    },
    "Footer_TelaCadastro": {
      "Facebook_1": 5,
      "Instagram_1": 4,
      "Linkedin_1": 3,
      "Rectangle3_4": 0,
      "Todos os direitos reservados_3": 6,
      "Twitter_1": 1,
      "Youtube_1": 2
    },
    "Footer_TelaCadastro2": {
      "Facebook_3": 5,
      "Instagram_3": 4,
      "Linkedin_3": 3,
      "Rectangle3_5": 0,
      "Todos os direitos reservados_5": 6,
      "Twitter_3": 1,
      "Youtube_3": 2
    },
    "Footer_TelaCadastro3": {
      "Facebook_4": 5,
      "Instagram_4": 4,
      "Linkedin_4": 3,
      "Rectangle3_17": 0,
      "Todos os direitos reservados_6": 6,
      "Twitter_4": 1,
      "Youtube_4": 2
    },
    "Footer_TelaLogin": {
      "Facebook": 5,
      "Instagram": 4,
      "Linkedin": 3,
      "Rectangle3_2": 0,
      "Todos os direitos reservados_2": 6,
      "Twitter": 1,
      "Youtube": 2
    },
    "Footer_Turma": {
      "Facebook_11": 5,
      "Instagram_11": 4,
      "Linkedin_11": 3,
      "Rectangle3_44": 0,
      "Todos os direitos reservados_13": 6,
      "Twitter_11": 1,
      "Youtube_11": 2
    },
    "Footer_VisNotasFrequencia": {
      "Facebook_13": 5,
      "Instagram_13": 4,
      "Linkedin_13": 3,
      "Rectangle3_48": 0,
      "Todos os direitos reservados_15": 6,
      "Twitter_13": 1,
      "Youtube_13": 2
    },
    "Header_Atividade": {
      "Icon2_14": 2,
      "Image12_20": 0,
      "Rectangle3_41": 1
    },
    "Header_Atividade_1": {
      "Icon2_25": 2,
      "Image12_31": 0,
      "Rectangle3_62": 1
    },
    "Header_Avisos": {
      "Icon2_13": 2,
      "Image12_19": 0,
      "Rectangle3_39": 1
    },
    "Header_Avisos_1": {
      "Icon2_20": 2,
      "Image12_26": 0,
      "Rectangle3_52": 1
    },
    "Header_Avisos_2": {
      "Icon2_23": 2,
      "Image12_29": 0,
      "Rectangle3_58": 1
    },
    "Header_Avisos_3": {
      "Icon2_24": 2,
      "Image12_30": 0,
      "Rectangle3_60": 1
    },
    "Header_Calendario": {
      "Icon2_19": 2,
      "Image12_25": 0,
      "Rectangle3_51": 1
    },
    "Header_CursoDisciplinas": {
      "Icon2_15": 2,
      "Image12_21": 0,
      "Rectangle3_43": 1
    },
    "Header_Home": {
      "Icon2_4": 2,
      "Image12_17": 0,
      "Rectangle3_34": 1
    },
    "Header_NotasFrequencia": {
      "Icon2_17": 2,
      "Image12_23": 0,
      "Rectangle3_47": 1
    },
    "Header_NotasFrequencia_1": {
      "Icon2_21": 2,
      "Image12_27": 0,
      "Rectangle3_54": 1
    },
    "Header_NotasFrequencia_2": {
      "Icon2_22": 2,
      "Image12_28": 0,
      "Rectangle3_56": 1
    },
    "Header_SucessoCadastro": {
      "Image12_16": 0,
      "Rectangle3_32": 1
    },
    "Header_TelaCadastro1": {
      "Image12_1": 0,
      "Rectangle3_1": 1
    },
    "Header_TelaCadastro2": {
      "Image12_2": 0,
      "Rectangle3_3": 1
    },
    "Header_TelaCadastro3": {
      "Image12_8": 0,
      "Rectangle3_16": 1
    },
    "Header_TelaLogin": {
      "Image12": 0,
      "Rectangle3": 1
    },
    "Header_Turma": {
      "Icon2_16": 2,
      "Image12_22": 0,
      "Rectangle3_45": 1
    },
    "Header_VisNotasFrequencia": {
      "Icon2_18": 2,
      "Image12_24": 0,
      "Rectangle3_49": 1
    },
    "Meu perfil": {
      "Button3_7": 1,
      "Button3_8": 5,
      "Icon3": 3,
      "Image3_2": 0,
      "Image3_3": 4,
      "Label10": 2
    },
    "Paginacao_1": {
      "Pag<_1": 3,
      "Pag>_1": 4,
      "Pag1_1": 0,
      "Pag3_1": 1,
      "Pag4_1": 2
    },
    "Paginacao_2": {
      "Pag<_2": 2,
      "Pag>_2": 3,
      "Pag3_2": 0,
      "Pag4_2": 1
    },
    "Perfil": {
      "Image16": 1,
      "Label5": 0
    },
    "Politica Privacidade": {
      "Aceito a": 0,
      "Politica de privacidade": 1,
      "Timetable": 2
    },
    "Titulo_Atividade": {
      "Image25_4": 0,
      "Label1_7": 1
    },
    "Titulo_Atividade_1": {
      "Image25_9": 0,
      "Label1_12": 1
    },
    "Titulo_Avisos": {
      "Image3_4": 1,
      "Label1_6": 0
    },
    "Titulo_Avisos_1": {
      "Image3_5": 1,
      "Label1_8": 0
    },
    "Titulo_Avisos_2": {
      "Image3_7": 1,
      "Label1_9": 0
    },
    "Titulo_Avisos_3": {
      "Image3_8": 1,
      "Label1_10": 0
    },
    "Titulo_TelaCadastro1": {
      "Image1": 0,
      "Label1": 1
    },
    "Titulo_TelaCadastro2": {
      "Image1_1": 0,
      "Label1_1": 1
    },
    "Titulo_TelaCadastro3": {
      "Image1_3": 0,
      "Label1_5": 1
    },
    "UltimasAtividades": {
      "Icon2_1": 5,
      "Label1_4": 1,
      "Label8_2": 2,
      "Label9_2": 3,
      "Label9_3": 0,
      "Rectangle1_5": 4
    }
  },
  "OrderPcfTemplate": {},
  "OrderTemplate": {},
  "OrderXMLTemplate": {
    "arrow": 5,
    "button": 7,
    "checkbox": 12,
    "combobox": 9,
    "datepicker": 10,
    "dropdown": 8,
    "form": 3,
    "gallery": 11,
    "icon": 6,
    "image": 1,
    "label": 2,
    "rectangle": 0,
    "text": 4
  },
  "OverridablePropertiesEntry": {
    "Aceito a": {},
    "App": {},
    "Arrow1": {},
    "Arrow1_1": {},
    "Arrow2": {},
    "Arrow2_1": {},
    "Atividade1": {},
    "Atividade2": {},
    "Atividades": {},
    "Aviso1": {},
    "Aviso2": {},
    "Aviso3": {},
    "Aviso4": {},
    "Body2": {},
    "Button1": {},
    "Button1_1": {},
    "Button1_10": {},
    "Button1_12": {},
    "Button1_13": {},
    "Button1_14": {},
    "Button1_15": {},
    "Button1_16": {},
    "Button1_17": {},
    "Button1_18": {},
    "Button1_19": {},
    "Button1_20": {},
    "Button1_4": {},
    "Button1_5": {},
    "Button1_9": {},
    "Button2": {},
    "Button3_3": {},
    "Button3_4": {},
    "Button3_5": {},
    "Button3_6": {},
    "Button3_7": {},
    "Button3_8": {},
    "Button3_9": {},
    "Button4": {},
    "Button4_1": {},
    "Button4_2": {},
    "Button4_3": {},
    "Button5": {},
    "Button5_1": {},
    "Button5_2": {},
    "Button6": {},
    "Button6_1": {},
    "Calendario": {},
    "Checkbox2": {},
    "ConfirmaEmail": {},
    "Confirmar E-mail_DataCard1": {},
    "Confirmar Senha_DataCard1": {},
    "ConfirmarSenha": {},
    "CPF_DataCard1": {},
    "Data Nascimento_DataCard1": {},
    "DataCardKey1": {},
    "DataCardKey10": {},
    "DataCardKey3": {},
    "DataCardKey4": {},
    "DataCardKey5": {},
    "DataCardKey6": {},
    "DataCardKey7": {},
    "DataCardKey8": {},
    "DataCardKey9": {},
    "DataCardValue10": {},
    "DataCardValue7": {},
    "DataCardValue8": {},
    "DataCardValue9": {},
    "DateValue1": {},
    "DigitarSenha": {},
    "E-mail": {},
    "E-mail_DataCard1": {},
    "entradaEmail": {},
    "ErrorMessage1": {},
    "ErrorMessage2": {},
    "ErrorMessage3": {},
    "ErrorMessage4": {},
    "ErrorMessage5": {},
    "ErrorMessage6": {},
    "ErrorMessage7": {},
    "ErrorMessage8": {},
    "ErrorMessage9": {},
    "Esqueci senha | Suporte": {},
    "Facebook": {},
    "Facebook_1": {},
    "Facebook_10": {},
    "Facebook_11": {},
    "Facebook_12": {},
    "Facebook_13": {},
    "Facebook_14": {},
    "Facebook_15": {},
    "Facebook_16": {},
    "Facebook_17": {},
    "Facebook_18": {},
    "Facebook_19": {},
    "Facebook_20": {},
    "Facebook_3": {},
    "Facebook_4": {},
    "Facebook_5": {},
    "Facebook_6": {},
    "Facebook_8": {},
    "Facebook_9": {},
    "Ferramentas": {},
    "Footer_Atividade": {},
    "Footer_Atividade_1": {},
    "Footer_Avisos": {},
    "Footer_Avisos_1": {},
    "Footer_Avisos_2": {},
    "Footer_Avisos_3": {},
    "Footer_Calendario": {},
    "Footer_CursoDisciplinas": {},
    "Footer_Home": {},
    "Footer_NotasFrequencia": {},
    "Footer_NotasFrequencia_1": {},
    "Footer_NotasFrequencia_2": {},
    "Footer_SucessoCadastro": {},
    "Footer_TelaCadastro": {},
    "Footer_TelaCadastro2": {},
    "Footer_TelaCadastro3": {},
    "Footer_TelaLogin": {},
    "Footer_Turma": {},
    "Footer_VisNotasFrequencia": {},
    "FormDados": {},
    "FormLogin": {},
    "Gallery1": {},
    "Gallery2": {},
    "galleryTemplate1": {},
    "galleryTemplate2": {},
    "Header_Atividade": {},
    "Header_Atividade_1": {},
    "Header_Avisos": {},
    "Header_Avisos_1": {},
    "Header_Avisos_2": {},
    "Header_Avisos_3": {},
    "Header_Calendario": {},
    "Header_CursoDisciplinas": {},
    "Header_Home": {},
    "Header_NotasFrequencia": {},
    "Header_NotasFrequencia_1": {},
    "Header_NotasFrequencia_2": {},
    "Header_SucessoCadastro": {},
    "Header_TelaCadastro1": {},
    "Header_TelaCadastro2": {},
    "Header_TelaCadastro3": {},
    "Header_TelaLogin": {},
    "Header_Turma": {},
    "Header_VisNotasFrequencia": {},
    "HourValue1": {},
    "Icon1": {},
    "Icon2": {},
    "Icon2_1": {},
    "Icon2_13": {},
    "Icon2_14": {},
    "Icon2_15": {},
    "Icon2_16": {},
    "Icon2_17": {},
    "Icon2_18": {},
    "Icon2_19": {},
    "Icon2_2": {},
    "Icon2_20": {},
    "Icon2_21": {},
    "Icon2_22": {},
    "Icon2_23": {},
    "Icon2_24": {},
    "Icon2_25": {},
    "Icon2_3": {},
    "Icon2_4": {},
    "Icon3": {},
    "Icon3_1": {},
    "Icon4": {},
    "Icon5": {},
    "Image1": {},
    "Image1_1": {},
    "Image1_3": {},
    "Image12": {},
    "Image12_1": {},
    "Image12_16": {},
    "Image12_17": {},
    "Image12_19": {},
    "Image12_2": {},
    "Image12_20": {},
    "Image12_21": {},
    "Image12_22": {},
    "Image12_23": {},
    "Image12_24": {},
    "Image12_25": {},
    "Image12_26": {},
    "Image12_27": {},
    "Image12_28": {},
    "Image12_29": {},
    "Image12_30": {},
    "Image12_31": {},
    "Image12_8": {},
    "Image13": {},
    "Image16": {},
    "Image21": {},
    "Image22": {},
    "Image23": {},
    "Image24": {},
    "Image25": {},
    "Image25_1": {},
    "Image25_2": {},
    "Image25_3": {},
    "Image25_4": {},
    "Image25_5": {},
    "Image25_6": {},
    "Image25_7": {},
    "Image25_9": {},
    "Image3_1": {},
    "Image3_2": {},
    "Image3_3": {},
    "Image3_4": {},
    "Image3_5": {},
    "Image3_6": {},
    "Image3_7": {},
    "Image3_8": {},
    "Image5": {},
    "Image6": {},
    "Instagram": {},
    "Instagram_1": {},
    "Instagram_10": {},
    "Instagram_11": {},
    "Instagram_12": {},
    "Instagram_13": {},
    "Instagram_14": {},
    "Instagram_15": {},
    "Instagram_16": {},
    "Instagram_17": {},
    "Instagram_18": {},
    "Instagram_19": {},
    "Instagram_20": {},
    "Instagram_3": {},
    "Instagram_4": {},
    "Instagram_5": {},
    "Instagram_6": {},
    "Instagram_8": {},
    "Instagram_9": {},
    "Já tem cadastro": {},
    "Label1": {},
    "Label1_1": {},
    "Label1_10": {},
    "Label1_11": {},
    "Label1_12": {},
    "Label1_15": {},
    "Label1_16": {},
    "Label1_17": {},
    "Label1_18": {},
    "Label1_19": {},
    "Label1_20": {},
    "Label1_21": {},
    "Label1_22": {},
    "Label1_23": {},
    "Label1_4": {},
    "Label1_5": {},
    "Label1_6": {},
    "Label1_7": {},
    "Label1_8": {},
    "Label1_9": {},
    "Label10": {},
    "Label10_1": {},
    "Label12_1": {},
    "Label13_1": {},
    "Label14_1": {},
    "Label15": {},
    "Label15_1": {},
    "Label17": {},
    "Label18": {},
    "Label19": {},
    "Label19_1": {},
    "Label19_2": {},
    "Label19_3": {},
    "Label19_4": {},
    "Label19_5": {},
    "Label19_6": {},
    "Label19_7": {},
    "Label2": {},
    "Label20": {},
    "Label20_1": {},
    "Label20_2": {},
    "Label20_3": {},
    "Label21": {},
    "Label21_1": {},
    "Label21_2": {},
    "Label22": {},
    "Label22_1": {},
    "Label23": {},
    "Label23_1": {},
    "Label24": {},
    "Label24_1": {},
    "Label25": {},
    "Label25_1": {},
    "Label26": {},
    "Label27": {},
    "Label28": {},
    "Label3": {},
    "Label4": {},
    "Label5": {},
    "Label6": {},
    "Label6_1": {},
    "Label6_2": {},
    "Label6_3": {},
    "Label6_4": {},
    "Label7": {},
    "Label8_2": {},
    "Label8_3": {},
    "Label8_4": {},
    "Label8_5": {},
    "Label8_6": {},
    "Label8_7": {},
    "Label9_10": {},
    "Label9_11": {},
    "Label9_2": {},
    "Label9_3": {},
    "Label9_4": {},
    "Label9_5": {},
    "Label9_6": {},
    "Label9_7": {},
    "Label9_8": {},
    "Label9_9": {},
    "LabelNomeCurso": {},
    "lbErroConfirmaEmail": {},
    "lbErroEntradaEmail": {},
    "Linkedin": {},
    "Linkedin_1": {},
    "Linkedin_10": {},
    "Linkedin_11": {},
    "Linkedin_12": {},
    "Linkedin_13": {},
    "Linkedin_14": {},
    "Linkedin_15": {},
    "Linkedin_16": {},
    "Linkedin_17": {},
    "Linkedin_18": {},
    "Linkedin_19": {},
    "Linkedin_20": {},
    "Linkedin_3": {},
    "Linkedin_4": {},
    "Linkedin_5": {},
    "Linkedin_6": {},
    "Linkedin_8": {},
    "Linkedin_9": {},
    "lstCursos": {},
    "lstCursos_1": {},
    "lstCursos_2": {},
    "lstDisciplinas": {},
    "Meu perfil": {},
    "MinuteValue1": {},
    "MuralAvisos1": {},
    "MuralAvisos2": {},
    "Não tem cadastro": {},
    "NextArrow4": {},
    "NextArrow5": {},
    "Nome Completo_DataCard1": {},
    "Nome Social_DataCard1": {},
    "NotasFrequencia": {},
    "Pag<_1": {},
    "Pag<_2": {},
    "Pag>_1": {},
    "Pag>_2": {},
    "Pag1_1": {},
    "Pag3_1": {},
    "Pag3_2": {},
    "Pag4_1": {},
    "Pag4_2": {},
    "Paginacao_1": {},
    "Paginacao_2": {},
    "PaginaInativa": {},
    "Perfil": {},
    "Politica de privacidade": {},
    "Politica Privacidade": {},
    "Rectangle1_10": {},
    "Rectangle1_2": {},
    "Rectangle1_5": {},
    "Rectangle1_6": {},
    "Rectangle1_7": {},
    "Rectangle1_8": {},
    "Rectangle1_9": {},
    "Rectangle2": {},
    "Rectangle3": {},
    "Rectangle3_1": {},
    "Rectangle3_14": {},
    "Rectangle3_15": {},
    "Rectangle3_16": {},
    "Rectangle3_17": {},
    "Rectangle3_2": {},
    "Rectangle3_3": {},
    "Rectangle3_32": {},
    "Rectangle3_33": {},
    "Rectangle3_34": {},
    "Rectangle3_35": {},
    "Rectangle3_38": {},
    "Rectangle3_39": {},
    "Rectangle3_4": {},
    "Rectangle3_40": {},
    "Rectangle3_41": {},
    "Rectangle3_42": {},
    "Rectangle3_43": {},
    "Rectangle3_44": {},
    "Rectangle3_45": {},
    "Rectangle3_46": {},
    "Rectangle3_47": {},
    "Rectangle3_48": {},
    "Rectangle3_49": {},
    "Rectangle3_5": {},
    "Rectangle3_50": {},
    "Rectangle3_51": {},
    "Rectangle3_52": {},
    "Rectangle3_53": {},
    "Rectangle3_54": {},
    "Rectangle3_55": {},
    "Rectangle3_56": {},
    "Rectangle3_57": {},
    "Rectangle3_58": {},
    "Rectangle3_59": {},
    "Rectangle3_60": {},
    "Rectangle3_61": {},
    "Rectangle3_62": {},
    "Rectangle3_63": {},
    "Senha": {},
    "Senha_DataCard1": {},
    "SenhaIncorreta": {},
    "Separator1": {},
    "Separator5": {},
    "Separator6": {},
    "Sexo_DataCard1": {},
    "StarVisible1": {},
    "StarVisible2": {},
    "StarVisible3": {},
    "StarVisible4": {},
    "StarVisible5": {},
    "StarVisible6": {},
    "StarVisible7": {},
    "StarVisible8": {},
    "StarVisible9": {},
    "Subtitle3": {},
    "Subtitle4": {},
    "SucessoCadastro": {},
    "TelaAcesso": {},
    "TelaCadastro1": {},
    "TelaCadastro2": {},
    "TelaCadastro3": {},
    "TelaLogin": {},
    "TelaMenu": {},
    "TextInput1": {},
    "TextInputEmail": {},
    "TextInputNotasFaltas": {},
    "TextInputSenha": {},
    "Timetable": {},
    "Title4": {},
    "Title5": {},
    "Titulo_Atividade": {},
    "Titulo_Atividade_1": {},
    "Titulo_Avisos": {},
    "Titulo_Avisos_1": {},
    "Titulo_Avisos_2": {},
    "Titulo_Avisos_3": {},
    "Titulo_TelaCadastro1": {},
    "Titulo_TelaCadastro2": {},
    "Titulo_TelaCadastro3": {},
    "Todos os direitos reservados": {},
    "Todos os direitos reservados_10": {},
    "Todos os direitos reservados_11": {},
    "Todos os direitos reservados_12": {},
    "Todos os direitos reservados_13": {},
    "Todos os direitos reservados_14": {},
    "Todos os direitos reservados_15": {},
    "Todos os direitos reservados_16": {},
    "Todos os direitos reservados_17": {},
    "Todos os direitos reservados_18": {},
    "Todos os direitos reservados_19": {},
    "Todos os direitos reservados_2": {},
    "Todos os direitos reservados_20": {},
    "Todos os direitos reservados_21": {},
    "Todos os direitos reservados_22": {},
    "Todos os direitos reservados_3": {},
    "Todos os direitos reservados_5": {},
    "Todos os direitos reservados_6": {},
    "Todos os direitos reservados_7": {},
    "Todos os direitos reservados_8": {},
    "TurmaInativa": {},
    "Twitter": {},
    "Twitter_1": {},
    "Twitter_10": {},
    "Twitter_11": {},
    "Twitter_12": {},
    "Twitter_13": {},
    "Twitter_14": {},
    "Twitter_15": {},
    "Twitter_16": {},
    "Twitter_17": {},
    "Twitter_18": {},
    "Twitter_19": {},
    "Twitter_20": {},
    "Twitter_3": {},
    "Twitter_4": {},
    "Twitter_5": {},
    "Twitter_6": {},
    "Twitter_8": {},
    "Twitter_9": {},
    "TxtCep": {},
    "TxtCep_1": {},
    "TxtCep_2": {},
    "TxtCep_3": {},
    "TxtCep_4": {},
    "TxtCep_5": {},
    "UltimasAtividades": {},
    "Visualizar Notas e Frequência": {},
    "Youtube": {},
    "Youtube_1": {},
    "Youtube_10": {},
    "Youtube_11": {},
    "Youtube_12": {},
    "Youtube_13": {},
    "Youtube_14": {},
    "Youtube_15": {},
    "Youtube_16": {},
    "Youtube_17": {},
    "Youtube_18": {},
    "Youtube_19": {},
    "Youtube_20": {},
    "Youtube_3": {},
    "Youtube_4": {},
    "Youtube_5": {},
    "Youtube_6": {},
    "Youtube_8": {},
    "Youtube_9": {}
  },
  "PCFDynamicSchemaForIRRetrievalEntry": {},
  "PublishOrderIndices": {
    "Aceito a": 130,
    "App": 0,
    "Arrow1": 54,
    "Arrow1_1": 99,
    "Arrow2": 98,
    "Arrow2_1": 135,
    "Atividade1": 0,
    "Atividade2": 0,
    "Atividades": 0,
    "Aviso1": 0,
    "Aviso2": 0,
    "Aviso3": 0,
    "Aviso4": 0,
    "Body2": 204,
    "Button1": 2,
    "Button1_1": 4,
    "Button1_10": 452,
    "Button1_12": 254,
    "Button1_13": 433,
    "Button1_14": 324,
    "Button1_15": 152,
    "Button1_16": 495,
    "Button1_17": 343,
    "Button1_18": 392,
    "Button1_19": 412,
    "Button1_20": 275,
    "Button1_4": 15,
    "Button1_5": 134,
    "Button1_9": 472,
    "Button2": 148,
    "Button3_3": 179,
    "Button3_4": 181,
    "Button3_5": 183,
    "Button3_6": 185,
    "Button3_7": 172,
    "Button3_8": 174,
    "Button3_9": 189,
    "Button4": 293,
    "Button4_1": 297,
    "Button4_2": 365,
    "Button4_3": 361,
    "Button5": 369,
    "Button5_1": 304,
    "Button5_2": 372,
    "Button6": 225,
    "Button6_1": 233,
    "Calendario": 0,
    "Checkbox2": 129,
    "ConfirmaEmail": 40,
    "Confirmar E-mail_DataCard1": 37,
    "Confirmar Senha_DataCard1": 47,
    "ConfirmarSenha": 50,
    "CPF_DataCard1": 80,
    "Data Nascimento_DataCard1": 90,
    "DataCardKey1": 92,
    "DataCardKey10": 87,
    "DataCardKey3": 39,
    "DataCardKey4": 49,
    "DataCardKey5": 44,
    "DataCardKey6": 34,
    "DataCardKey7": 72,
    "DataCardKey8": 77,
    "DataCardKey9": 82,
    "DataCardValue10": 88,
    "DataCardValue7": 73,
    "DataCardValue8": 78,
    "DataCardValue9": 83,
    "DateValue1": 93,
    "DigitarSenha": 45,
    "E-mail": 10,
    "E-mail_DataCard1": 32,
    "entradaEmail": 35,
    "ErrorMessage1": 97,
    "ErrorMessage2": 41,
    "ErrorMessage3": 51,
    "ErrorMessage4": 46,
    "ErrorMessage5": 36,
    "ErrorMessage6": 74,
    "ErrorMessage7": 79,
    "ErrorMessage8": 84,
    "ErrorMessage9": 89,
    "Esqueci senha | Suporte": 16,
    "Facebook": 19,
    "Facebook_1": 57,
    "Facebook_10": 475,
    "Facebook_11": 455,
    "Facebook_12": 208,
    "Facebook_13": 497,
    "Facebook_14": 436,
    "Facebook_15": 346,
    "Facebook_16": 307,
    "Facebook_17": 375,
    "Facebook_18": 395,
    "Facebook_19": 415,
    "Facebook_20": 278,
    "Facebook_3": 102,
    "Facebook_4": 138,
    "Facebook_5": 155,
    "Facebook_6": 236,
    "Facebook_8": 327,
    "Facebook_9": 257,
    "Ferramentas": 175,
    "Footer_Atividade": 256,
    "Footer_Atividade_1": 277,
    "Footer_Avisos": 326,
    "Footer_Avisos_1": 345,
    "Footer_Avisos_2": 394,
    "Footer_Avisos_3": 414,
    "Footer_Calendario": 435,
    "Footer_CursoDisciplinas": 474,
    "Footer_Home": 235,
    "Footer_NotasFrequencia": 207,
    "Footer_NotasFrequencia_1": 306,
    "Footer_NotasFrequencia_2": 374,
    "Footer_SucessoCadastro": 154,
    "Footer_TelaCadastro": 56,
    "Footer_TelaCadastro2": 101,
    "Footer_TelaCadastro3": 137,
    "Footer_TelaLogin": 18,
    "Footer_Turma": 454,
    "Footer_VisNotasFrequencia": 485,
    "FormDados": 69,
    "FormLogin": 31,
    "Gallery1": 427,
    "Gallery2": 199,
    "galleryTemplate1": 428,
    "galleryTemplate2": 200,
    "Header_Atividade": 243,
    "Header_Atividade_1": 264,
    "Header_Avisos": 314,
    "Header_Avisos_1": 334,
    "Header_Avisos_2": 382,
    "Header_Avisos_3": 402,
    "Header_Calendario": 422,
    "Header_CursoDisciplinas": 462,
    "Header_Home": 215,
    "Header_NotasFrequencia": 191,
    "Header_NotasFrequencia_1": 285,
    "Header_NotasFrequencia_2": 353,
    "Header_SucessoCadastro": 145,
    "Header_TelaCadastro1": 26,
    "Header_TelaCadastro2": 64,
    "Header_TelaCadastro3": 109,
    "Header_TelaLogin": 7,
    "Header_Turma": 443,
    "Header_VisNotasFrequencia": 483,
    "HourValue1": 94,
    "Icon1": 118,
    "Icon2": 198,
    "Icon2_1": 231,
    "Icon2_13": 316,
    "Icon2_14": 245,
    "Icon2_15": 464,
    "Icon2_16": 445,
    "Icon2_17": 193,
    "Icon2_18": 484,
    "Icon2_19": 424,
    "Icon2_2": 218,
    "Icon2_20": 336,
    "Icon2_21": 287,
    "Icon2_22": 355,
    "Icon2_23": 384,
    "Icon2_24": 404,
    "Icon2_25": 266,
    "Icon2_3": 223,
    "Icon2_4": 217,
    "Icon3": 170,
    "Icon3_1": 177,
    "Icon4": 163,
    "Icon5": 188,
    "Image1": 30,
    "Image1_1": 68,
    "Image1_3": 113,
    "Image12": 8,
    "Image12_1": 27,
    "Image12_16": 146,
    "Image12_17": 216,
    "Image12_19": 315,
    "Image12_2": 65,
    "Image12_20": 244,
    "Image12_21": 463,
    "Image12_22": 444,
    "Image12_23": 192,
    "Image12_24": 482,
    "Image12_25": 423,
    "Image12_26": 335,
    "Image12_27": 286,
    "Image12_28": 354,
    "Image12_29": 383,
    "Image12_30": 403,
    "Image12_31": 265,
    "Image12_8": 110,
    "Image13": 9,
    "Image16": 164,
    "Image21": 178,
    "Image22": 180,
    "Image23": 182,
    "Image24": 184,
    "Image25": 466,
    "Image25_1": 469,
    "Image25_2": 446,
    "Image25_3": 195,
    "Image25_4": 248,
    "Image25_5": 425,
    "Image25_6": 149,
    "Image25_7": 487,
    "Image25_9": 269,
    "Image3_1": 288,
    "Image3_2": 171,
    "Image3_3": 173,
    "Image3_4": 319,
    "Image3_5": 339,
    "Image3_6": 356,
    "Image3_7": 387,
    "Image3_8": 407,
    "Image5": 187,
    "Image6": 0,
    "Instagram": 20,
    "Instagram_1": 58,
    "Instagram_10": 476,
    "Instagram_11": 456,
    "Instagram_12": 209,
    "Instagram_13": 498,
    "Instagram_14": 437,
    "Instagram_15": 347,
    "Instagram_16": 308,
    "Instagram_17": 376,
    "Instagram_18": 396,
    "Instagram_19": 416,
    "Instagram_20": 279,
    "Instagram_3": 103,
    "Instagram_4": 139,
    "Instagram_5": 156,
    "Instagram_6": 237,
    "Instagram_8": 328,
    "Instagram_9": 258,
    "Já tem cadastro": 1,
    "Label1": 29,
    "Label1_1": 67,
    "Label1_10": 406,
    "Label1_11": 219,
    "Label1_12": 268,
    "Label1_15": 470,
    "Label1_16": 447,
    "Label1_17": 194,
    "Label1_18": 289,
    "Label1_19": 426,
    "Label1_20": 357,
    "Label1_21": 486,
    "Label1_22": 467,
    "Label1_23": 150,
    "Label1_4": 227,
    "Label1_5": 112,
    "Label1_6": 318,
    "Label1_7": 247,
    "Label1_8": 338,
    "Label1_9": 386,
    "Label10": 169,
    "Label10_1": 176,
    "Label12_1": 489,
    "Label13_1": 490,
    "Label14_1": 492,
    "Label15": 196,
    "Label15_1": 493,
    "Label17": 488,
    "Label18": 491,
    "Label19": 322,
    "Label19_1": 320,
    "Label19_2": 340,
    "Label19_3": 342,
    "Label19_4": 388,
    "Label19_5": 390,
    "Label19_6": 408,
    "Label19_7": 410,
    "Label2": 116,
    "Label20": 321,
    "Label20_1": 341,
    "Label20_2": 389,
    "Label20_3": 409,
    "Label21": 323,
    "Label21_1": 391,
    "Label21_2": 411,
    "Label22": 253,
    "Label22_1": 274,
    "Label23": 252,
    "Label23_1": 273,
    "Label24": 251,
    "Label24_1": 272,
    "Label25": 249,
    "Label25_1": 270,
    "Label26": 448,
    "Label27": 449,
    "Label28": 450,
    "Label3": 147,
    "Label4": 114,
    "Label5": 165,
    "Label6": 119,
    "Label6_1": 120,
    "Label6_2": 123,
    "Label6_3": 125,
    "Label6_4": 126,
    "Label7": 465,
    "Label8_2": 230,
    "Label8_3": 222,
    "Label8_4": 291,
    "Label8_5": 295,
    "Label8_6": 359,
    "Label8_7": 363,
    "Label9_10": 224,
    "Label9_11": 271,
    "Label9_2": 232,
    "Label9_3": 229,
    "Label9_4": 221,
    "Label9_5": 250,
    "Label9_6": 292,
    "Label9_7": 296,
    "Label9_8": 364,
    "Label9_9": 360,
    "LabelNomeCurso": 167,
    "lbErroConfirmaEmail": 53,
    "lbErroEntradaEmail": 52,
    "Linkedin": 21,
    "Linkedin_1": 59,
    "Linkedin_10": 477,
    "Linkedin_11": 457,
    "Linkedin_12": 210,
    "Linkedin_13": 499,
    "Linkedin_14": 438,
    "Linkedin_15": 348,
    "Linkedin_16": 309,
    "Linkedin_17": 377,
    "Linkedin_18": 397,
    "Linkedin_19": 417,
    "Linkedin_20": 280,
    "Linkedin_3": 104,
    "Linkedin_4": 140,
    "Linkedin_5": 157,
    "Linkedin_6": 238,
    "Linkedin_8": 329,
    "Linkedin_9": 259,
    "lstCursos": 468,
    "lstCursos_1": 451,
    "lstCursos_2": 151,
    "lstDisciplinas": 471,
    "Meu perfil": 168,
    "MinuteValue1": 96,
    "MuralAvisos1": 0,
    "MuralAvisos2": 0,
    "Não tem cadastro": 3,
    "NextArrow4": 430,
    "NextArrow5": 203,
    "Nome Completo_DataCard1": 70,
    "Nome Social_DataCard1": 75,
    "NotasFrequencia": 0,
    "Pag<_1": 298,
    "Pag<_2": 366,
    "Pag>_1": 301,
    "Pag>_2": 368,
    "Pag1_1": 300,
    "Pag3_1": 302,
    "Pag3_2": 370,
    "Pag4_1": 303,
    "Pag4_2": 371,
    "Paginacao_1": 299,
    "Paginacao_2": 367,
    "PaginaInativa": 0,
    "Perfil": 166,
    "Politica de privacidade": 132,
    "Politica Privacidade": 131,
    "Rectangle1_10": 220,
    "Rectangle1_2": 494,
    "Rectangle1_5": 228,
    "Rectangle1_6": 290,
    "Rectangle1_7": 358,
    "Rectangle1_8": 294,
    "Rectangle1_9": 362,
    "Rectangle2": 162,
    "Rectangle3": 6,
    "Rectangle3_1": 25,
    "Rectangle3_14": 161,
    "Rectangle3_15": 186,
    "Rectangle3_16": 108,
    "Rectangle3_17": 136,
    "Rectangle3_2": 17,
    "Rectangle3_3": 63,
    "Rectangle3_32": 144,
    "Rectangle3_33": 153,
    "Rectangle3_34": 214,
    "Rectangle3_35": 234,
    "Rectangle3_38": 325,
    "Rectangle3_39": 313,
    "Rectangle3_4": 55,
    "Rectangle3_40": 255,
    "Rectangle3_41": 242,
    "Rectangle3_42": 473,
    "Rectangle3_43": 461,
    "Rectangle3_44": 453,
    "Rectangle3_45": 442,
    "Rectangle3_46": 206,
    "Rectangle3_47": 190,
    "Rectangle3_48": 496,
    "Rectangle3_49": 481,
    "Rectangle3_5": 100,
    "Rectangle3_50": 434,
    "Rectangle3_51": 421,
    "Rectangle3_52": 333,
    "Rectangle3_53": 344,
    "Rectangle3_54": 284,
    "Rectangle3_55": 305,
    "Rectangle3_56": 352,
    "Rectangle3_57": 373,
    "Rectangle3_58": 381,
    "Rectangle3_59": 393,
    "Rectangle3_60": 401,
    "Rectangle3_61": 413,
    "Rectangle3_62": 263,
    "Rectangle3_63": 276,
    "Senha": 12,
    "Senha_DataCard1": 42,
    "SenhaIncorreta": 14,
    "Separator1": 95,
    "Separator5": 432,
    "Separator6": 205,
    "Sexo_DataCard1": 85,
    "StarVisible1": 91,
    "StarVisible2": 38,
    "StarVisible3": 48,
    "StarVisible4": 43,
    "StarVisible5": 33,
    "StarVisible6": 71,
    "StarVisible7": 76,
    "StarVisible8": 81,
    "StarVisible9": 86,
    "Subtitle3": 202,
    "Subtitle4": 431,
    "SucessoCadastro": 0,
    "TelaAcesso": 0,
    "TelaCadastro1": 0,
    "TelaCadastro2": 0,
    "TelaCadastro3": 0,
    "TelaLogin": 0,
    "TelaMenu": 0,
    "TextInput1": 115,
    "TextInputEmail": 11,
    "TextInputNotasFaltas": 197,
    "TextInputSenha": 13,
    "Timetable": 133,
    "Title4": 429,
    "Title5": 201,
    "Titulo_Atividade": 246,
    "Titulo_Atividade_1": 267,
    "Titulo_Avisos": 317,
    "Titulo_Avisos_1": 337,
    "Titulo_Avisos_2": 385,
    "Titulo_Avisos_3": 405,
    "Titulo_TelaCadastro1": 28,
    "Titulo_TelaCadastro2": 66,
    "Titulo_TelaCadastro3": 111,
    "Todos os direitos reservados": 5,
    "Todos os direitos reservados_10": 332,
    "Todos os direitos reservados_11": 262,
    "Todos os direitos reservados_12": 480,
    "Todos os direitos reservados_13": 460,
    "Todos os direitos reservados_14": 213,
    "Todos os direitos reservados_15": 502,
    "Todos os direitos reservados_16": 441,
    "Todos os direitos reservados_17": 351,
    "Todos os direitos reservados_18": 312,
    "Todos os direitos reservados_19": 380,
    "Todos os direitos reservados_2": 24,
    "Todos os direitos reservados_20": 400,
    "Todos os direitos reservados_21": 420,
    "Todos os direitos reservados_22": 283,
    "Todos os direitos reservados_3": 62,
    "Todos os direitos reservados_5": 107,
    "Todos os direitos reservados_6": 143,
    "Todos os direitos reservados_7": 160,
    "Todos os direitos reservados_8": 241,
    "TurmaInativa": 0,
    "Twitter": 23,
    "Twitter_1": 61,
    "Twitter_10": 479,
    "Twitter_11": 459,
    "Twitter_12": 212,
    "Twitter_13": 501,
    "Twitter_14": 440,
    "Twitter_15": 350,
    "Twitter_16": 311,
    "Twitter_17": 379,
    "Twitter_18": 399,
    "Twitter_19": 419,
    "Twitter_20": 282,
    "Twitter_3": 106,
    "Twitter_4": 142,
    "Twitter_5": 159,
    "Twitter_6": 240,
    "Twitter_8": 331,
    "Twitter_9": 261,
    "TxtCep": 117,
    "TxtCep_1": 121,
    "TxtCep_2": 124,
    "TxtCep_3": 122,
    "TxtCep_4": 127,
    "TxtCep_5": 128,
    "UltimasAtividades": 226,
    "Visualizar Notas e Frequência": 0,
    "Youtube": 22,
    "Youtube_1": 60,
    "Youtube_10": 478,
    "Youtube_11": 458,
    "Youtube_12": 211,
    "Youtube_13": 500,
    "Youtube_14": 439,
    "Youtube_15": 349,
    "Youtube_16": 310,
    "Youtube_17": 378,
    "Youtube_18": 398,
    "Youtube_19": 418,
    "Youtube_20": 281,
    "Youtube_3": 105,
    "Youtube_4": 141,
    "Youtube_5": 158,
    "Youtube_6": 239,
    "Youtube_8": 330,
    "Youtube_9": 260
  },
  "ResourcesJsonIndices": {
    "Image-10": 20,
    "Image-18": 18,
    "Image-19 1": 41,
    "Image-2": 3,
    "Image-2_1": 4,
    "Image-20": 27,
    "Image-24": 21,
    "Image-25": 28,
    "Image-26": 31,
    "Image-27": 15,
    "Image-28": 33,
    "Image-29": 30,
    "Image-32": 32,
    "Image-7": 29,
    "Image-bg-btn": 10,
    "Image-bg-btn_1": 13,
    "Image-Ellipse 1": 25,
    "Image-EnsinoSuperior": 26,
    "Image-Esqueci a senha _ Suporte login": 34,
    "Image-Footer": 7,
    "Image-FooterIcones": 22,
    "Image-Group 3": 9,
    "Image-Group 3_1": 19,
    "Image-Header liso": 5,
    "Image-icon1": 1,
    "Image-icons8-facebook-90": 36,
    "Image-icons8-instagram-128": 37,
    "Image-icons8-linkedin-128": 38,
    "Image-icons8-twitter-squared-64": 40,
    "Image-icons8-youtube-squared-128": 39,
    "Image-Já tem cadastro_": 11,
    "Image-meuperfil": 24,
    "Image-Não tem cadastro_": 12,
    "Image-NATAL 2022": 8,
    "Image-NATAL 2022_1": 14,
    "Image-partebaixo": 2,
    "Image-privacidade": 35,
    "Image-Rectangle 26": 6,
    "Image-Rectangle 27": 23,
    "Image-SampleImage": 0,
    "Image-Section 3": 17,
    "Image-Todos os Direitos Reservados - 2022": 16
  },
  "RuleScreenIdWithoutScreen": {},
  "TemplateVersions": {},
  "VolatileProperties": {
    "AnalysisLoadTime": 1.8705952,
    "ControlCount": {
      "arrow": 4,
      "button": 32,
      "checkbox": 1,
      "combobox": 1,
      "datepicker": 1,
      "dropdown": 6,
      "form": 2,
      "gallery": 2,
      "galleryTemplate": 2,
      "group": 54,
      "icon": 25,
      "image": 142,
      "label": 154,
      "rectangle": 50,
      "screen": 21,
      "text": 18,
      "typedDataCard": 9
    },
    "DeserializationLoadTime": 6.0971151,
    "ErrorCount": 1
  },
  "WasLocalDatabaseReferencesEmpty": false
}