{
  "ComponentIndexes": {},
  "ControlUniqueGuids": {},
  "ControlUniqueIds": {
    "Aceito a": 348,
    "App": 1,
    "Arrow1": 143,
    "Arrow1_1": 189,
    "Arrow2": 188,
    "Arrow2_1": 352,
    "Atividade1": 64,
    "Atividade2": 580,
    "Atividades": 221,
    "Aviso1": 200,
    "Aviso2": 420,
    "Aviso3": 518,
    "Aviso4": 539,
    "Button1": 111,
    "Button1_1": 113,
    "Button1_10": 33,
    "Button1_11": 54,
    "Button1_12": 75,
    "Button1_13": 98,
    "Button1_14": 210,
    "Button1_15": 370,
    "Button1_16": 283,
    "Button1_17": 430,
    "Button1_18": 528,
    "Button1_19": 549,
    "Button1_20": 591,
    "Button1_4": 259,
    "Button1_5": 351,
    "Button1_9": 13,
    "Button2": 369,
    "Button3_3": 399,
    "Button3_4": 401,
    "Button3_5": 403,
    "Button3_6": 405,
    "Button3_7": 389,
    "Button3_8": 391,
    "Button3_9": 408,
    "Button4": 472,
    "Button4_1": 478,
    "Button4_2": 499,
    "Button4_3": 495,
    "Button5": 516,
    "Button5_1": 517,
    "Button5_2": 560,
    "Button6": 579,
    "Button6_1": 602,
    "Calendario": 86,
    "Checkbox2": 347,
    "ConfirmaEmail": 129,
    "Confirmar E-mail_DataCard1": 126,
    "Confirmar Senha_DataCard1": 136,
    "ConfirmarSenha": 139,
    "CPF_DataCard1": 170,
    "Data Nascimento_DataCard1": 180,
    "DataCardKey1": 182,
    "DataCardKey10": 177,
    "DataCardKey3": 128,
    "DataCardKey4": 138,
    "DataCardKey5": 133,
    "DataCardKey6": 123,
    "DataCardKey7": 162,
    "DataCardKey8": 167,
    "DataCardKey9": 172,
    "DataCardValue10": 178,
    "DataCardValue7": 163,
    "DataCardValue8": 168,
    "DataCardValue9": 173,
    "DateValue1": 183,
    "DigitarSenha": 134,
    "E-mail": 254,
    "E-mail_DataCard1": 121,
    "entradaEmail": 124,
    "ErrorMessage1": 187,
    "ErrorMessage2": 130,
    "ErrorMessage3": 140,
    "ErrorMessage4": 135,
    "ErrorMessage5": 125,
    "ErrorMessage6": 164,
    "ErrorMessage7": 169,
    "ErrorMessage8": 174,
    "ErrorMessage9": 179,
    "Esqueci senha | Suporte": 260,
    "Facebook": 262,
    "Facebook_1": 145,
    "Facebook_10": 15,
    "Facebook_11": 35,
    "Facebook_12": 56,
    "Facebook_13": 285,
    "Facebook_14": 100,
    "Facebook_15": 432,
    "Facebook_16": 454,
    "Facebook_17": 501,
    "Facebook_18": 530,
    "Facebook_19": 551,
    "Facebook_20": 593,
    "Facebook_3": 191,
    "Facebook_4": 354,
    "Facebook_5": 372,
    "Facebook_6": 240,
    "Facebook_8": 212,
    "Facebook_9": 77,
    "Ferramentas": 409,
    "Footer_Atividade": 83,
    "Footer_Atividade_1": 599,
    "Footer_Avisos": 218,
    "Footer_Avisos_1": 438,
    "Footer_Avisos_2": 536,
    "Footer_Avisos_3": 557,
    "Footer_Calendario": 106,
    "Footer_CursoDisciplinas": 21,
    "Footer_Home": 248,
    "Footer_NotasFrequencia": 62,
    "Footer_NotasFrequencia_1": 460,
    "Footer_NotasFrequencia_2": 513,
    "Footer_SucessoCadastro": 379,
    "Footer_TelaCadastro": 153,
    "Footer_TelaCadastro2": 199,
    "Footer_TelaCadastro3": 363,
    "Footer_TelaLogin": 268,
    "Footer_Turma": 41,
    "Footer_VisNotasFrequencia": 291,
    "FormDados": 159,
    "FormLogin": 120,
    "Gallery1": 92,
    "galleryTemplate1": 93,
    "Header_Atividade": 85,
    "Header_Atividade_1": 601,
    "Header_Avisos": 219,
    "Header_Avisos_1": 439,
    "Header_Avisos_2": 537,
    "Header_Avisos_3": 558,
    "Header_Calendario": 107,
    "Header_CursoDisciplinas": 22,
    "Header_Home": 247,
    "Header_NotasFrequencia": 63,
    "Header_NotasFrequencia_1": 461,
    "Header_NotasFrequencia_2": 514,
    "Header_SucessoCadastro": 378,
    "Header_TelaCadastro1": 151,
    "Header_TelaCadastro2": 198,
    "Header_TelaCadastro3": 362,
    "Header_TelaLogin": 269,
    "Header_Turma": 42,
    "Header_VisNotasFrequencia": 292,
    "HourValue1": 184,
    "Icon1": 336,
    "Icon2_1": 236,
    "Icon2_13": 203,
    "Icon2_14": 67,
    "Icon2_15": 6,
    "Icon2_16": 26,
    "Icon2_17": 46,
    "Icon2_18": 273,
    "Icon2_19": 89,
    "Icon2_2": 225,
    "Icon2_20": 423,
    "Icon2_21": 444,
    "Icon2_22": 489,
    "Icon2_23": 521,
    "Icon2_24": 542,
    "Icon2_25": 583,
    "Icon2_3": 578,
    "Icon2_4": 224,
    "Icon3": 387,
    "Icon3_1": 393,
    "Icon4": 383,
    "Image1": 119,
    "Image1_1": 158,
    "Image1_3": 331,
    "Image12": 252,
    "Image12_1": 117,
    "Image12_16": 366,
    "Image12_17": 223,
    "Image12_19": 202,
    "Image12_2": 156,
    "Image12_20": 66,
    "Image12_21": 5,
    "Image12_22": 25,
    "Image12_23": 45,
    "Image12_24": 272,
    "Image12_25": 88,
    "Image12_26": 422,
    "Image12_27": 443,
    "Image12_28": 488,
    "Image12_29": 520,
    "Image12_30": 541,
    "Image12_31": 582,
    "Image12_8": 329,
    "Image13": 253,
    "Image16": 384,
    "Image21": 398,
    "Image22": 400,
    "Image23": 402,
    "Image24": 404,
    "Image25": 7,
    "Image25_1": 10,
    "Image25_2": 27,
    "Image25_3": 48,
    "Image25_4": 69,
    "Image25_5": 90,
    "Image25_6": 416,
    "Image25_7": 275,
    "Image25_8": 417,
    "Image25_9": 585,
    "Image3_1": 463,
    "Image3_2": 388,
    "Image3_3": 390,
    "Image3_4": 205,
    "Image3_5": 425,
    "Image3_6": 490,
    "Image3_7": 523,
    "Image3_8": 544,
    "Image5": 407,
    "Image6": 109,
    "Instagram": 263,
    "Instagram_1": 146,
    "Instagram_10": 16,
    "Instagram_11": 36,
    "Instagram_12": 57,
    "Instagram_13": 286,
    "Instagram_14": 101,
    "Instagram_15": 433,
    "Instagram_16": 455,
    "Instagram_17": 502,
    "Instagram_18": 531,
    "Instagram_19": 552,
    "Instagram_20": 594,
    "Instagram_3": 192,
    "Instagram_4": 355,
    "Instagram_5": 373,
    "Instagram_6": 241,
    "Instagram_8": 213,
    "Instagram_9": 78,
    "Já tem cadastro": 110,
    "Label1": 118,
    "Label1_1": 157,
    "Label1_10": 543,
    "Label1_11": 570,
    "Label1_12": 584,
    "Label1_15": 11,
    "Label1_16": 28,
    "Label1_17": 47,
    "Label1_18": 467,
    "Label1_19": 91,
    "Label1_20": 491,
    "Label1_21": 274,
    "Label1_22": 8,
    "Label1_23": 415,
    "Label1_24": 418,
    "Label1_4": 232,
    "Label1_5": 330,
    "Label1_6": 204,
    "Label1_7": 68,
    "Label1_8": 424,
    "Label1_9": 522,
    "Label10": 386,
    "Label10_1": 392,
    "Label12": 49,
    "Label12_1": 277,
    "Label13": 50,
    "Label13_1": 278,
    "Label14": 51,
    "Label14_1": 280,
    "Label15": 52,
    "Label15_1": 281,
    "Label17": 276,
    "Label18": 279,
    "Label19": 208,
    "Label19_1": 206,
    "Label19_2": 426,
    "Label19_3": 428,
    "Label19_4": 524,
    "Label19_5": 526,
    "Label19_6": 545,
    "Label19_7": 547,
    "Label2": 334,
    "Label20": 207,
    "Label20_1": 427,
    "Label20_2": 525,
    "Label20_3": 546,
    "Label21": 209,
    "Label21_1": 527,
    "Label21_2": 548,
    "Label22": 74,
    "Label22_1": 590,
    "Label23": 73,
    "Label23_1": 589,
    "Label24": 72,
    "Label24_1": 588,
    "Label25": 70,
    "Label25_1": 586,
    "Label26": 29,
    "Label27": 30,
    "Label28": 31,
    "Label3": 368,
    "Label4": 332,
    "Label5": 385,
    "Label6": 337,
    "Label6_1": 338,
    "Label6_2": 341,
    "Label6_3": 343,
    "Label6_4": 344,
    "Label7": 419,
    "Label8_2": 235,
    "Label8_3": 572,
    "Label8_4": 468,
    "Label8_5": 477,
    "Label8_6": 493,
    "Label8_7": 497,
    "Label9_10": 573,
    "Label9_11": 587,
    "Label9_2": 237,
    "Label9_3": 234,
    "Label9_4": 577,
    "Label9_5": 71,
    "Label9_6": 471,
    "Label9_7": 476,
    "Label9_8": 498,
    "Label9_9": 494,
    "lbErroConfirmaEmail": 142,
    "lbErroEntradaEmail": 141,
    "Linkedin": 264,
    "Linkedin_1": 147,
    "Linkedin_10": 17,
    "Linkedin_11": 37,
    "Linkedin_12": 58,
    "Linkedin_13": 287,
    "Linkedin_14": 102,
    "Linkedin_15": 434,
    "Linkedin_16": 456,
    "Linkedin_17": 503,
    "Linkedin_18": 532,
    "Linkedin_19": 553,
    "Linkedin_20": 595,
    "Linkedin_3": 193,
    "Linkedin_4": 356,
    "Linkedin_5": 374,
    "Linkedin_6": 242,
    "Linkedin_8": 214,
    "Linkedin_9": 79,
    "lstCursos": 9,
    "lstCursos_1": 32,
    "lstCursos_2": 413,
    "lstDisciplinas": 12,
    "lstDisciplinas_1": 53,
    "lstDisciplinas_2": 414,
    "Meu perfil": 411,
    "MinuteValue1": 186,
    "MuralAvisos1": 441,
    "MuralAvisos2": 486,
    "Não tem cadastro": 112,
    "NextArrow4": 95,
    "Nome Completo_DataCard1": 160,
    "Nome Social_DataCard1": 165,
    "NotasFrequencia": 43,
    "Pag<_1": 483,
    "Pag<_2": 507,
    "Pag>_1": 484,
    "Pag>_2": 509,
    "Pag1_1": 479,
    "Pag3_1": 481,
    "Pag3_2": 511,
    "Pag4_1": 482,
    "Pag4_2": 512,
    "Paginacao_1": 485,
    "Paginacao_2": 515,
    "PaginaInativa": 3,
    "Perfil": 410,
    "Politica de privacidade": 349,
    "Politica Privacidade": 360,
    "Rectangle1_10": 575,
    "Rectangle1_2": 282,
    "Rectangle1_5": 233,
    "Rectangle1_6": 469,
    "Rectangle1_7": 492,
    "Rectangle1_8": 475,
    "Rectangle1_9": 496,
    "Rectangle2": 382,
    "Rectangle3": 251,
    "Rectangle3_1": 116,
    "Rectangle3_14": 381,
    "Rectangle3_15": 406,
    "Rectangle3_16": 328,
    "Rectangle3_17": 353,
    "Rectangle3_2": 261,
    "Rectangle3_3": 155,
    "Rectangle3_32": 365,
    "Rectangle3_33": 371,
    "Rectangle3_34": 222,
    "Rectangle3_35": 239,
    "Rectangle3_38": 211,
    "Rectangle3_39": 201,
    "Rectangle3_4": 144,
    "Rectangle3_40": 76,
    "Rectangle3_41": 65,
    "Rectangle3_42": 14,
    "Rectangle3_43": 4,
    "Rectangle3_44": 34,
    "Rectangle3_45": 24,
    "Rectangle3_46": 55,
    "Rectangle3_47": 44,
    "Rectangle3_48": 284,
    "Rectangle3_49": 271,
    "Rectangle3_5": 190,
    "Rectangle3_50": 99,
    "Rectangle3_51": 87,
    "Rectangle3_52": 421,
    "Rectangle3_53": 431,
    "Rectangle3_54": 442,
    "Rectangle3_55": 453,
    "Rectangle3_56": 487,
    "Rectangle3_57": 500,
    "Rectangle3_58": 519,
    "Rectangle3_59": 529,
    "Rectangle3_60": 540,
    "Rectangle3_61": 550,
    "Rectangle3_62": 581,
    "Rectangle3_63": 592,
    "Senha": 256,
    "Senha_DataCard1": 131,
    "SenhaIncorreta": 258,
    "Separator1": 185,
    "Separator5": 97,
    "Sexo_DataCard1": 175,
    "StarVisible1": 181,
    "StarVisible2": 127,
    "StarVisible3": 137,
    "StarVisible4": 132,
    "StarVisible5": 122,
    "StarVisible6": 161,
    "StarVisible7": 166,
    "StarVisible8": 171,
    "StarVisible9": 176,
    "Subtitle4": 96,
    "SucessoCadastro": 364,
    "TelaAcesso": 108,
    "TelaCadastro1": 115,
    "TelaCadastro2": 154,
    "TelaCadastro3": 327,
    "TelaLogin": 250,
    "TelaMenu": 380,
    "TextInput1": 333,
    "TextInputEmail": 255,
    "TextInputSenha": 257,
    "Timetable": 350,
    "Title4": 94,
    "Titulo_Atividade": 84,
    "Titulo_Atividade_1": 600,
    "Titulo_Avisos": 220,
    "Titulo_Avisos_1": 440,
    "Titulo_Avisos_2": 538,
    "Titulo_Avisos_3": 559,
    "Titulo_TelaCadastro1": 152,
    "Titulo_TelaCadastro2": 197,
    "Titulo_TelaCadastro3": 361,
    "Todos os direitos reservados": 114,
    "Todos os direitos reservados_10": 217,
    "Todos os direitos reservados_11": 82,
    "Todos os direitos reservados_12": 20,
    "Todos os direitos reservados_13": 40,
    "Todos os direitos reservados_14": 61,
    "Todos os direitos reservados_15": 290,
    "Todos os direitos reservados_16": 105,
    "Todos os direitos reservados_17": 437,
    "Todos os direitos reservados_18": 459,
    "Todos os direitos reservados_19": 506,
    "Todos os direitos reservados_2": 267,
    "Todos os direitos reservados_20": 535,
    "Todos os direitos reservados_21": 556,
    "Todos os direitos reservados_22": 598,
    "Todos os direitos reservados_3": 150,
    "Todos os direitos reservados_5": 196,
    "Todos os direitos reservados_6": 359,
    "Todos os direitos reservados_7": 377,
    "Todos os direitos reservados_8": 245,
    "TurmaInativa": 23,
    "Twitter": 266,
    "Twitter_1": 149,
    "Twitter_10": 19,
    "Twitter_11": 39,
    "Twitter_12": 60,
    "Twitter_13": 289,
    "Twitter_14": 104,
    "Twitter_15": 436,
    "Twitter_16": 458,
    "Twitter_17": 505,
    "Twitter_18": 534,
    "Twitter_19": 555,
    "Twitter_20": 597,
    "Twitter_3": 195,
    "Twitter_4": 358,
    "Twitter_5": 376,
    "Twitter_6": 244,
    "Twitter_8": 216,
    "Twitter_9": 81,
    "TxtCep": 335,
    "TxtCep_1": 339,
    "TxtCep_2": 342,
    "TxtCep_3": 340,
    "TxtCep_4": 345,
    "TxtCep_5": 346,
    "UltimasAtividades": 249,
    "Visualizar Notas e Frequência": 270,
    "Youtube": 265,
    "Youtube_1": 148,
    "Youtube_10": 18,
    "Youtube_11": 38,
    "Youtube_12": 59,
    "Youtube_13": 288,
    "Youtube_14": 103,
    "Youtube_15": 435,
    "Youtube_16": 457,
    "Youtube_17": 504,
    "Youtube_18": 533,
    "Youtube_19": 554,
    "Youtube_20": 596,
    "Youtube_3": 194,
    "Youtube_4": 357,
    "Youtube_5": 375,
    "Youtube_6": 243,
    "Youtube_8": 215,
    "Youtube_9": 80
  },
  "FunctionParamsInvariantScripts": {},
  "FunctionParamsInvariantScriptsOnInstances": {},
  "HeaderLastSavedDateTimeUTC": "03/08/2023 20:02:25",
  "IsLegacyComponentAllowGlobalScopeCase": false,
  "LocalConnectionIDReferences": {
    "011faafa-c34d-46b3-87be-7ccdd485d9cb": "\"/providers/microsoft.powerapps/apis/shared_sharepointonline/connections/e9911849802646e781efbefd2f311fa9\"",
    "50471254-8922-4980-9b2b-f48fb005d5a9": "\"/providers/microsoft.powerapps/apis/shared_logicflows/connections/a51f0f040a8c4391acf88880ace98876-61c895ebdf0a9d83\""
  },
  "LocalDatabaseReferencesAsEmpty": false,
  "LocalResourceFileNames": {
    "10": "272c64ae-f126-4499-8722-3304d0d850d6.png",
    "18": "2befdcbc-41e2-4812-b049-fc2c81e018b7.png",
    "19 1": "58b83cfb-5e7f-4a58-86ca-dfeef9b282c3.png",
    "2": "5a8b0286-e92b-4903-bac5-c2103a384a20.png",
    "2_1": "140b3580-dd46-441f-ae91-ee1f2e7b5907.png",
    "20": "8c8b29e7-21d4-4179-84e0-ea3840ea1043.png",
    "24": "498cd539-7246-4918-b13c-6d72a2dac2e3.png",
    "25": "c5180adc-19a5-4a9c-8b42-732de98f1175.png",
    "26": "02d55896-fa71-4e16-920a-9bcbeefab880.png",
    "27": "b4968b17-ffe5-43f9-b194-c073e426a465.png",
    "28": "bed9fe89-22f9-4f89-92bd-8ae7097888cf.png",
    "29": "5d350645-a7f5-4b98-906c-56d304453a0d.png",
    "32": "25b62121-fa79-4bbe-9771-b8749b6862d1.png",
    "7": "b5e2a8c4-4d47-4c46-bb65-d821add64b0e.png",
    "bg-btn": "0df5e589-e17c-4a11-b560-88a64c03b3e1.png",
    "bg-btn_1": "9aa4c843-e4a5-4d04-b2ec-a4655696e7d8.png",
    "Ellipse 1": "5ac0995f-6846-4dbc-b347-56db6d374852.png",
    "EnsinoSuperior": "f56fbdca-6be8-4e56-905a-177264442da6.png",
    "Esqueci a senha _ Suporte login": "b9023b64-3584-49eb-89bb-22c61c414160.png",
    "Footer": "c03a0313-1778-4a44-9438-269a28e6b638.png",
    "FooterIcones": "cc4f2ed9-4225-49f3-9ece-7524febc0ee1.png",
    "Group 3": "13c6bef3-45ca-44c0-b369-a463be3a309d.png",
    "Group 3_1": "aab301e2-2800-44f8-b222-58440cf8fd3d.png",
    "Header liso": "3585d97f-d130-4acb-b027-7b9dcdbb3e9e.png",
    "icon1": "9d506386-b319-4af0-a4f9-98fa05e3be07.jpg",
    "icons8-facebook-90": "33e23749-7bbd-4530-b6bc-9b64e752a46d.png",
    "icons8-instagram-128": "4800a3eb-2b8c-4e6c-9f51-12e318aa22ef.png",
    "icons8-linkedin-128": "add7fe31-5bed-4a25-b6bf-1317ffc45d60.png",
    "icons8-twitter-squared-64": "7bdef63b-d165-4739-93db-985741f1cefb.png",
    "icons8-youtube-squared-128": "5ce6c74c-7904-44b6-840e-670bc7c3d26d.png",
    "Já tem cadastro_": "3257cea4-819a-4eb4-8c5f-38ccc80d307f.png",
    "meuperfil": "5a2a6c43-4dbb-4a6e-ba25-5f9cd762fbc6.png",
    "Não tem cadastro_": "2aed7137-4b43-4654-a817-67bd300a6a1b.png",
    "NATAL 2022": "837c4769-3204-413c-9c22-0382199f1d30.png",
    "NATAL 2022_1": "2b2d9078-77ca-45a2-a31b-49f302c5d437.png",
    "partebaixo": "227cf407-8a63-460e-93bf-36c7706da5e4.jpg",
    "privacidade": "d8cdc662-3752-4a74-9f3b-909a8177254e.jpg",
    "Rectangle 26": "15db3776-5d81-409a-b5dd-99aac5994832.png",
    "Rectangle 27": "42ee8732-a2bf-4697-9a06-7af6432ff0bf.png",
    "Section 3": "93fbc403-e275-411e-9cc3-39fe942238af.png",
    "Todos os Direitos Reservados - 2022": "b044b0f5-0b4b-4bc5-be07-b4fe9e4299ef.png"
  },
  "LocalResourceRootPaths": {
    "10": "https://docserverpwaprodsbr.blob.core.windows.net/3c74b911-6228-469d-a077-080eeb3ae54d-1/resource/Assets0Images0272c64ae-f126-4499-8722-3304d0d850d6.png?sv=2018-03-28&sr=b&sig=CIOnX6mHv0PRtJYGlr3o%2B%2F%2FL5XJhLK%2B8%2B239hLLLPII%3D&spr=https&se=2023-03-09T18%3A05%3A40Z&sp=r",
    "18": "https://docserverpwaprodsbr.blob.core.windows.net/3c74b911-6228-469d-a077-080eeb3ae54d-1/resource/Assets0Images02befdcbc-41e2-4812-b049-fc2c81e018b7.png?sv=2018-03-28&sr=b&sig=OLS8DtDKQcmPipLYLmXJZ1jR8NOvIW%2FXNDvF3YR7rjA%3D&spr=https&se=2023-03-09T18%3A05%3A40Z&sp=r",
    "19 1": "https://docserverpwaprodsbr.blob.core.windows.net/3c74b911-6228-469d-a077-080eeb3ae54d-1/resource/Assets0Images058b83cfb-5e7f-4a58-86ca-dfeef9b282c3.png?sv=2018-03-28&sr=b&sig=4TNRIJhPcJROJKX2bDKGaUKnqEH8GMEzw5tFphwmXUs%3D&spr=https&se=2023-03-09T18%3A05%3A40Z&sp=r",
    "2": "https://docserverpwaprodsbr.blob.core.windows.net/3c74b911-6228-469d-a077-080eeb3ae54d-1/resource/Assets0Images05a8b0286-e92b-4903-bac5-c2103a384a20.png?sv=2018-03-28&sr=b&sig=GAD7QnUH%2FD7UNM7RoTPLzM8cYuJRuNl2BTGL38PBYrw%3D&spr=https&se=2023-03-09T18%3A05%3A40Z&sp=r",
    "2_1": "https://docserverpwaprodsbr.blob.core.windows.net/3c74b911-6228-469d-a077-080eeb3ae54d-1/resource/Assets0Images0140b3580-dd46-441f-ae91-ee1f2e7b5907.png?sv=2018-03-28&sr=b&sig=q8VxX%2Bi6gy6d8bySwrMQMDWjOUv8dij5sPgSo54iBds%3D&spr=https&se=2023-03-09T18%3A05%3A40Z&sp=r",
    "20": "https://docserverpwaprodsbr.blob.core.windows.net/3c74b911-6228-469d-a077-080eeb3ae54d-1/resource/Assets0Images08c8b29e7-21d4-4179-84e0-ea3840ea1043.png?sv=2018-03-28&sr=b&sig=8hy6IsxXmAigbc8RVpsFKewZcIWHDRqrv6EBO%2FFtGuw%3D&spr=https&se=2023-03-09T18%3A05%3A40Z&sp=r",
    "24": "https://docserverpwaprodsbr.blob.core.windows.net/3c74b911-6228-469d-a077-080eeb3ae54d-1/resource/Assets0Images0498cd539-7246-4918-b13c-6d72a2dac2e3.png?sv=2018-03-28&sr=b&sig=27KKXxuSz9qTL1AkfBP2kTv0n8s7Y4HGisxZdYzlCs8%3D&spr=https&se=2023-03-09T18%3A05%3A40Z&sp=r",
    "25": "https://docserverpwaprodsbr.blob.core.windows.net/3c74b911-6228-469d-a077-080eeb3ae54d-1/resource/Assets0Images0c5180adc-19a5-4a9c-8b42-732de98f1175.png?sv=2018-03-28&sr=b&sig=Xzc8avzlQhNXTvwJe8MGC0iC2KmlmBkzwIpSIkkm%2F3k%3D&spr=https&se=2023-03-09T18%3A05%3A40Z&sp=r",
    "26": "https://docserverpwaprodsbr.blob.core.windows.net/3c74b911-6228-469d-a077-080eeb3ae54d-1/resource/Assets0Images002d55896-fa71-4e16-920a-9bcbeefab880.png?sv=2018-03-28&sr=b&sig=UZ0eiCw90%2F9%2BaD%2BMXPcuKeSv5tjNq4%2BiYZKzac78KK4%3D&spr=https&se=2023-03-09T18%3A05%3A40Z&sp=r",
    "27": "https://docserverpwaprodsbr.blob.core.windows.net/3c74b911-6228-469d-a077-080eeb3ae54d-1/resource/Assets0Images0b4968b17-ffe5-43f9-b194-c073e426a465.png?sv=2018-03-28&sr=b&sig=z3vnEOdmmnybxrY0MUkv2OPqiTrVqBl3hqVPSrvD0kU%3D&spr=https&se=2023-03-09T18%3A05%3A40Z&sp=r",
    "28": "https://docserverpwaprodsbr.blob.core.windows.net/3c74b911-6228-469d-a077-080eeb3ae54d-1/resource/Assets0Images0bed9fe89-22f9-4f89-92bd-8ae7097888cf.png?sv=2018-03-28&sr=b&sig=6bjzCIvyuylr2Px7cNGEZxXvXyM1qc9R8eTesLXb%2BIA%3D&spr=https&se=2023-03-09T18%3A05%3A40Z&sp=r",
    "29": "https://docserverpwaprodsbr.blob.core.windows.net/3c74b911-6228-469d-a077-080eeb3ae54d-1/resource/Assets0Images05d350645-a7f5-4b98-906c-56d304453a0d.png?sv=2018-03-28&sr=b&sig=452U9NpX0aMGk4MYKef%2BAjIg%2FqbHD4gcNWnxYY2rZc0%3D&spr=https&se=2023-03-09T18%3A05%3A40Z&sp=r",
    "32": "https://docserverpwaprodsbr.blob.core.windows.net/3c74b911-6228-469d-a077-080eeb3ae54d-1/resource/Assets0Images025b62121-fa79-4bbe-9771-b8749b6862d1.png?sv=2018-03-28&sr=b&sig=biubORhBjkB278p6f7p4QxAPV095ZSTuId%2FTN51CLS8%3D&spr=https&se=2023-03-09T18%3A05%3A40Z&sp=r",
    "7": "https://docserverpwaprodsbr.blob.core.windows.net/3c74b911-6228-469d-a077-080eeb3ae54d-1/resource/Assets0Images0b5e2a8c4-4d47-4c46-bb65-d821add64b0e.png?sv=2018-03-28&sr=b&sig=xDMJEKxufZklcs%2FN3zfbQuDwpU54w0OhQ%2FYoGTH5AH4%3D&spr=https&se=2023-03-09T18%3A05%3A40Z&sp=r",
    "bg-btn": "https://docserverpwaprodsbr.blob.core.windows.net/3c74b911-6228-469d-a077-080eeb3ae54d-1/resource/Assets0Images00df5e589-e17c-4a11-b560-88a64c03b3e1.png?sv=2018-03-28&sr=b&sig=Sk%2F3n0E63bT6zGVs0hSn3ZLBTKDBtjFvTn3KvO8pG2I%3D&spr=https&se=2023-03-09T18%3A05%3A40Z&sp=r",
    "bg-btn_1": "https://docserverpwaprodsbr.blob.core.windows.net/3c74b911-6228-469d-a077-080eeb3ae54d-1/resource/Assets0Images09aa4c843-e4a5-4d04-b2ec-a4655696e7d8.png?sv=2018-03-28&sr=b&sig=KN%2BZvFf8KXynTpXVkUv9LUWJgd72%2B%2BT2k9%2F%2F7vwti90%3D&spr=https&se=2023-03-09T18%3A05%3A40Z&sp=r",
    "Ellipse 1": "https://docserverpwaprodsbr.blob.core.windows.net/3c74b911-6228-469d-a077-080eeb3ae54d-1/resource/Assets0Images05ac0995f-6846-4dbc-b347-56db6d374852.png?sv=2018-03-28&sr=b&sig=MGqTBo%2B0h0vhbdQCaztXiUFhlT97owhADam2DAbbQW8%3D&spr=https&se=2023-03-09T18%3A05%3A40Z&sp=r",
    "EnsinoSuperior": "https://docserverpwaprodsbr.blob.core.windows.net/3c74b911-6228-469d-a077-080eeb3ae54d-1/resource/Assets0Images0f56fbdca-6be8-4e56-905a-177264442da6.png?sv=2018-03-28&sr=b&sig=eOhXeBaVFodp4invPTAwWNVG5Ii5LcYKkkO1jNqocGM%3D&spr=https&se=2023-03-09T18%3A05%3A40Z&sp=r",
    "Esqueci a senha _ Suporte login": "https://docserverpwaprodsbr.blob.core.windows.net/3c74b911-6228-469d-a077-080eeb3ae54d-1/resource/Assets0Images0b9023b64-3584-49eb-89bb-22c61c414160.png?sv=2018-03-28&sr=b&sig=OPpYAzZBvWo0XMM2I1OzOQiV6oaamQyewYUyEf1vl6A%3D&spr=https&se=2023-03-09T18%3A05%3A40Z&sp=r",
    "Footer": "https://docserverpwaprodsbr.blob.core.windows.net/3c74b911-6228-469d-a077-080eeb3ae54d-1/resource/Assets0Images0c03a0313-1778-4a44-9438-269a28e6b638.png?sv=2018-03-28&sr=b&sig=JS1BXEFo8wGRNkMZo6E%2FZtmfjNoAtXQmjwgQvQi02K4%3D&spr=https&se=2023-03-09T18%3A05%3A40Z&sp=r",
    "FooterIcones": "https://docserverpwaprodsbr.blob.core.windows.net/3c74b911-6228-469d-a077-080eeb3ae54d-1/resource/Assets0Images0cc4f2ed9-4225-49f3-9ece-7524febc0ee1.png?sv=2018-03-28&sr=b&sig=t9Ubj9x%2BiTtnop8X0sHu6sEq5xcvAxM%2FXt6vClG4rdg%3D&spr=https&se=2023-03-09T18%3A05%3A40Z&sp=r",
    "Group 3": "https://docserverpwaprodsbr.blob.core.windows.net/3c74b911-6228-469d-a077-080eeb3ae54d-1/resource/Assets0Images013c6bef3-45ca-44c0-b369-a463be3a309d.png?sv=2018-03-28&sr=b&sig=ETmS9fPTdqdL2oMeKKWI64TaYl8T2iJ8VZFqeNLAL7I%3D&spr=https&se=2023-03-09T18%3A05%3A40Z&sp=r",
    "Group 3_1": "https://docserverpwaprodsbr.blob.core.windows.net/3c74b911-6228-469d-a077-080eeb3ae54d-1/resource/Assets0Images0aab301e2-2800-44f8-b222-58440cf8fd3d.png?sv=2018-03-28&sr=b&sig=Jv8bQkg%2B9XqhzNisx94DsB6yAH58OOVPU0u0LUZAyRk%3D&spr=https&se=2023-03-09T18%3A05%3A40Z&sp=r",
    "Header liso": "https://docserverpwaprodsbr.blob.core.windows.net/3c74b911-6228-469d-a077-080eeb3ae54d-1/resource/Assets0Images03585d97f-d130-4acb-b027-7b9dcdbb3e9e.png?sv=2018-03-28&sr=b&sig=NKJsfr80JMOozDjMfu7OHrvWtxvkUBguAceqvgwCa%2Bw%3D&spr=https&se=2023-03-09T18%3A05%3A40Z&sp=r",
    "icon1": "https://docserverpwaprodsbr.blob.core.windows.net/3c74b911-6228-469d-a077-080eeb3ae54d-1/resource/Assets0Images09d506386-b319-4af0-a4f9-98fa05e3be07.jpg?sv=2018-03-28&sr=b&sig=%2F0Ehz6ophnUiKxrNXB8zCWhfwqt9EuPLxea9Qyq4pCs%3D&spr=https&se=2023-03-09T18%3A05%3A40Z&sp=r",
    "icons8-facebook-90": "https://docserverpwaprodsbr.blob.core.windows.net/3c74b911-6228-469d-a077-080eeb3ae54d-1/resource/Assets0Images033e23749-7bbd-4530-b6bc-9b64e752a46d.png?sv=2018-03-28&sr=b&sig=pkZLM%2FOtRlZf1KSX6wAoPo%2BcAkRuqtmorR4aNfGdisA%3D&spr=https&se=2023-03-09T18%3A05%3A40Z&sp=r",
    "icons8-instagram-128": "https://docserverpwaprodsbr.blob.core.windows.net/3c74b911-6228-469d-a077-080eeb3ae54d-1/resource/Assets0Images04800a3eb-2b8c-4e6c-9f51-12e318aa22ef.png?sv=2018-03-28&sr=b&sig=bT%2BxswBbLhhTqqt2WARpwdAKTwknb29yVkV0mVMXEMI%3D&spr=https&se=2023-03-09T18%3A05%3A40Z&sp=r",
    "icons8-linkedin-128": "https://docserverpwaprodsbr.blob.core.windows.net/3c74b911-6228-469d-a077-080eeb3ae54d-1/resource/Assets0Images0add7fe31-5bed-4a25-b6bf-1317ffc45d60.png?sv=2018-03-28&sr=b&sig=H9eVUj4hdZy4J74AFStjRoDkHI37x%2FtBRoE0%2Bzz73dg%3D&spr=https&se=2023-03-09T18%3A05%3A40Z&sp=r",
    "icons8-twitter-squared-64": "https://docserverpwaprodsbr.blob.core.windows.net/3c74b911-6228-469d-a077-080eeb3ae54d-1/resource/Assets0Images07bdef63b-d165-4739-93db-985741f1cefb.png?sv=2018-03-28&sr=b&sig=Df6%2BcTWYUlb7hmP4iiZgcDP6P5IJyDjR1wl3Wu5AkFc%3D&spr=https&se=2023-03-09T18%3A05%3A40Z&sp=r",
    "icons8-youtube-squared-128": "https://docserverpwaprodsbr.blob.core.windows.net/3c74b911-6228-469d-a077-080eeb3ae54d-1/resource/Assets0Images05ce6c74c-7904-44b6-840e-670bc7c3d26d.png?sv=2018-03-28&sr=b&sig=LbqGeOqRmRj5n1TTRUN%2FPEsEq%2FuH146F39G%2F6K4JlFE%3D&spr=https&se=2023-03-09T18%3A05%3A40Z&sp=r",
    "Já tem cadastro_": "https://docserverpwaprodsbr.blob.core.windows.net/3c74b911-6228-469d-a077-080eeb3ae54d-1/resource/Assets0Images03257cea4-819a-4eb4-8c5f-38ccc80d307f.png?sv=2018-03-28&sr=b&sig=PD78xifpivDjmWAfbDIe6kad%2Bfs2j0NR%2Bc6BoxpH7FQ%3D&spr=https&se=2023-03-09T18%3A05%3A40Z&sp=r",
    "meuperfil": "https://docserverpwaprodsbr.blob.core.windows.net/3c74b911-6228-469d-a077-080eeb3ae54d-1/resource/Assets0Images05a2a6c43-4dbb-4a6e-ba25-5f9cd762fbc6.png?sv=2018-03-28&sr=b&sig=%2FHZUS8fzpj7%2F1WGc76I36ufAO%2Fm1a3VcFIBv%2B3w8JJg%3D&spr=https&se=2023-03-09T18%3A05%3A40Z&sp=r",
    "Não tem cadastro_": "https://docserverpwaprodsbr.blob.core.windows.net/3c74b911-6228-469d-a077-080eeb3ae54d-1/resource/Assets0Images02aed7137-4b43-4654-a817-67bd300a6a1b.png?sv=2018-03-28&sr=b&sig=jww4gdv6sWoZSVFqOZEi5KLqVgY9dc4gp%2FhDa%2F4aN0o%3D&spr=https&se=2023-03-09T18%3A05%3A40Z&sp=r",
    "NATAL 2022": "https://docserverpwaprodsbr.blob.core.windows.net/3c74b911-6228-469d-a077-080eeb3ae54d-1/resource/Assets0Images0837c4769-3204-413c-9c22-0382199f1d30.png?sv=2018-03-28&sr=b&sig=DFCCpx6rRkCaynYbiYQRsz8iaiU%2FlFDXSH%2BTT8TT9lA%3D&spr=https&se=2023-03-09T18%3A05%3A40Z&sp=r",
    "NATAL 2022_1": "https://docserverpwaprodsbr.blob.core.windows.net/3c74b911-6228-469d-a077-080eeb3ae54d-1/resource/Assets0Images02b2d9078-77ca-45a2-a31b-49f302c5d437.png?sv=2018-03-28&sr=b&sig=m6TOJ35nBrDqeonrCdt6tMcyf17j%2BkmjdzAm%2BkLY40M%3D&spr=https&se=2023-03-09T18%3A05%3A40Z&sp=r",
    "partebaixo": "https://docserverpwaprodsbr.blob.core.windows.net/3c74b911-6228-469d-a077-080eeb3ae54d-1/resource/Assets0Images0227cf407-8a63-460e-93bf-36c7706da5e4.jpg?sv=2018-03-28&sr=b&sig=p4Z%2FbODT8Qq45HgmXq7Mx74a62GWji2spHj%2BUS3DXSM%3D&spr=https&se=2023-03-09T18%3A05%3A40Z&sp=r",
    "privacidade": "https://docserverpwaprodsbr.blob.core.windows.net/3c74b911-6228-469d-a077-080eeb3ae54d-1/resource/Assets0Images0d8cdc662-3752-4a74-9f3b-909a8177254e.jpg?sv=2018-03-28&sr=b&sig=%2BsLps8Rmfu0USvuv%2FpSLiElEk65CYU%2BcvQIA3XyPJvA%3D&spr=https&se=2023-03-09T18%3A05%3A40Z&sp=r",
    "Rectangle 26": "https://docserverpwaprodsbr.blob.core.windows.net/3c74b911-6228-469d-a077-080eeb3ae54d-1/resource/Assets0Images015db3776-5d81-409a-b5dd-99aac5994832.png?sv=2018-03-28&sr=b&sig=gfLC9oQQfS0e%2FDgmrMzT8yUR8WW6zJ9JIbhYa7BxXNQ%3D&spr=https&se=2023-03-09T18%3A05%3A40Z&sp=r",
    "Rectangle 27": "https://docserverpwaprodsbr.blob.core.windows.net/3c74b911-6228-469d-a077-080eeb3ae54d-1/resource/Assets0Images042ee8732-a2bf-4697-9a06-7af6432ff0bf.png?sv=2018-03-28&sr=b&sig=MMtAbTxzFB4Ge8lEDCmq%2BHg8Bcz2HQ%2B0O%2BPeOKAuPNU%3D&spr=https&se=2023-03-09T18%3A05%3A40Z&sp=r",
    "Section 3": "https://docserverpwaprodsbr.blob.core.windows.net/3c74b911-6228-469d-a077-080eeb3ae54d-1/resource/Assets0Images093fbc403-e275-411e-9cc3-39fe942238af.png?sv=2018-03-28&sr=b&sig=sPq9se%2FHOnaYPNH7ZjQhVBnFVAfG7y6MFUD0HTE%2F5JA%3D&spr=https&se=2023-03-09T18%3A05%3A40Z&sp=r",
    "Todos os Direitos Reservados - 2022": "https://docserverpwaprodsbr.blob.core.windows.net/3c74b911-6228-469d-a077-080eeb3ae54d-1/resource/Assets0Images0b044b0f5-0b4b-4bc5-be07-b4fe9e4299ef.png?sv=2018-03-28&sr=b&sig=j5uGiW%2Fa5YdMCUfEhMkWF4EI3O0iNVUtLTL0oeDs8S0%3D&spr=https&se=2023-03-09T18%3A05%3A40Z&sp=r"
  },
  "OldLogoFileName": "4zp03d1f.jpg",
  "OrderComponentMetadata": {},
  "OrderComponentTemplate": {},
  "OrderDataSource": {
    "Calendário TimeTable": 14,
    "CollectTeste": 15,
    "ComboBoxSample": 10,
    "ConsultaCep": 0,
    "CustomGallerySample": 8,
    "Dados Aluno": 12,
    "Dados Aluno\\cr65a_dadosaluno_cr65a_sexo": 3,
    "Dados Aluno\\cr65a_dadosaluno_statecode": 4,
    "Dados Aluno\\cr65a_dadosaluno_statuscode": 5,
    "Dados Aluno\\default.cds_cr65a_dadosaluno_views": 7,
    "DropDownSample": 9,
    "Login": 11,
    "Login\\cr65a_login_statecode": 1,
    "Login\\cr65a_login_statuscode": 2,
    "Login\\default.cds_cr65a_login_views": 6,
    "RadioSample": 13
  },
  "OrderGroupControls": {
    "Ferramentas": {
      "Button3_3": 3,
      "Button3_4": 2,
      "Button3_5": 1,
      "Button3_6": 0,
      "Icon3_1": 4,
      "Image21": 9,
      "Image22": 8,
      "Image23": 7,
      "Image24": 6,
      "Label10_1": 5
    },
    "Footer_Atividade": {
      "Facebook_9": 5,
      "Instagram_9": 4,
      "Linkedin_9": 3,
      "Rectangle3_40": 0,
      "Todos os direitos reservados_11": 6,
      "Twitter_9": 1,
      "Youtube_9": 2
    },
    "Footer_Atividade_1": {
      "Facebook_20": 5,
      "Instagram_20": 4,
      "Linkedin_20": 3,
      "Rectangle3_63": 0,
      "Todos os direitos reservados_22": 6,
      "Twitter_20": 1,
      "Youtube_20": 2
    },
    "Footer_Avisos": {
      "Facebook_8": 5,
      "Instagram_8": 4,
      "Linkedin_8": 3,
      "Rectangle3_38": 0,
      "Todos os direitos reservados_10": 6,
      "Twitter_8": 1,
      "Youtube_8": 2
    },
    "Footer_Avisos_1": {
      "Facebook_15": 5,
      "Instagram_15": 4,
      "Linkedin_15": 3,
      "Rectangle3_53": 0,
      "Todos os direitos reservados_17": 6,
      "Twitter_15": 1,
      "Youtube_15": 2
    },
    "Footer_Avisos_2": {
      "Facebook_18": 5,
      "Instagram_18": 4,
      "Linkedin_18": 3,
      "Rectangle3_59": 0,
      "Todos os direitos reservados_20": 6,
      "Twitter_18": 1,
      "Youtube_18": 2
    },
    "Footer_Avisos_3": {
      "Facebook_19": 5,
      "Instagram_19": 4,
      "Linkedin_19": 3,
      "Rectangle3_61": 0,
      "Todos os direitos reservados_21": 6,
      "Twitter_19": 1,
      "Youtube_19": 2
    },
    "Footer_Calendario": {
      "Facebook_14": 5,
      "Instagram_14": 4,
      "Linkedin_14": 3,
      "Rectangle3_50": 0,
      "Todos os direitos reservados_16": 6,
      "Twitter_14": 1,
      "Youtube_14": 2
    },
    "Footer_CursoDisciplinas": {
      "Facebook_10": 5,
      "Instagram_10": 4,
      "Linkedin_10": 3,
      "Rectangle3_42": 0,
      "Todos os direitos reservados_12": 6,
      "Twitter_10": 1,
      "Youtube_10": 2
    },
    "Footer_Home": {
      "Facebook_6": 5,
      "Instagram_6": 4,
      "Linkedin_6": 3,
      "Rectangle3_35": 0,
      "Todos os direitos reservados_8": 6,
      "Twitter_6": 1,
      "Youtube_6": 2
    },
    "Footer_NotasFrequencia": {
      "Facebook_12": 5,
      "Instagram_12": 4,
      "Linkedin_12": 3,
      "Rectangle3_46": 0,
      "Todos os direitos reservados_14": 6,
      "Twitter_12": 1,
      "Youtube_12": 2
    },
    "Footer_NotasFrequencia_1": {
      "Facebook_16": 5,
      "Instagram_16": 4,
      "Linkedin_16": 3,
      "Rectangle3_55": 0,
      "Todos os direitos reservados_18": 6,
      "Twitter_16": 1,
      "Youtube_16": 2
    },
    "Footer_NotasFrequencia_2": {
      "Facebook_17": 5,
      "Instagram_17": 4,
      "Linkedin_17": 3,
      "Rectangle3_57": 0,
      "Todos os direitos reservados_19": 6,
      "Twitter_17": 1,
      "Youtube_17": 2
    },
    "Footer_SucessoCadastro": {
      "Facebook_5": 5,
      "Instagram_5": 4,
      "Linkedin_5": 3,
      "Rectangle3_33": 0,
      "Todos os direitos reservados_7": 6,
      "Twitter_5": 1,
      "Youtube_5": 2
    },
    "Footer_TelaCadastro": {
      "Facebook_1": 5,
      "Instagram_1": 4,
      "Linkedin_1": 3,
      "Rectangle3_4": 0,
      "Todos os direitos reservados_3": 6,
      "Twitter_1": 1,
      "Youtube_1": 2
    },
    "Footer_TelaCadastro2": {
      "Facebook_3": 5,
      "Instagram_3": 4,
      "Linkedin_3": 3,
      "Rectangle3_5": 0,
      "Todos os direitos reservados_5": 6,
      "Twitter_3": 1,
      "Youtube_3": 2
    },
    "Footer_TelaCadastro3": {
      "Facebook_4": 5,
      "Instagram_4": 4,
      "Linkedin_4": 3,
      "Rectangle3_17": 0,
      "Todos os direitos reservados_6": 6,
      "Twitter_4": 1,
      "Youtube_4": 2
    },
    "Footer_TelaLogin": {
      "Facebook": 5,
      "Instagram": 4,
      "Linkedin": 3,
      "Rectangle3_2": 0,
      "Todos os direitos reservados_2": 6,
      "Twitter": 1,
      "Youtube": 2
    },
    "Footer_Turma": {
      "Facebook_11": 5,
      "Instagram_11": 4,
      "Linkedin_11": 3,
      "Rectangle3_44": 0,
      "Todos os direitos reservados_13": 6,
      "Twitter_11": 1,
      "Youtube_11": 2
    },
    "Footer_VisNotasFrequencia": {
      "Facebook_13": 5,
      "Instagram_13": 4,
      "Linkedin_13": 3,
      "Rectangle3_48": 0,
      "Todos os direitos reservados_15": 6,
      "Twitter_13": 1,
      "Youtube_13": 2
    },
    "Header_Atividade": {
      "Icon2_14": 2,
      "Image12_20": 0,
      "Rectangle3_41": 1
    },
    "Header_Atividade_1": {
      "Icon2_25": 2,
      "Image12_31": 0,
      "Rectangle3_62": 1
    },
    "Header_Avisos": {
      "Icon2_13": 2,
      "Image12_19": 0,
      "Rectangle3_39": 1
    },
    "Header_Avisos_1": {
      "Icon2_20": 2,
      "Image12_26": 0,
      "Rectangle3_52": 1
    },
    "Header_Avisos_2": {
      "Icon2_23": 2,
      "Image12_29": 0,
      "Rectangle3_58": 1
    },
    "Header_Avisos_3": {
      "Icon2_24": 2,
      "Image12_30": 0,
      "Rectangle3_60": 1
    },
    "Header_Calendario": {
      "Icon2_19": 2,
      "Image12_25": 0,
      "Rectangle3_51": 1
    },
    "Header_CursoDisciplinas": {
      "Icon2_15": 2,
      "Image12_21": 0,
      "Rectangle3_43": 1
    },
    "Header_Home": {
      "Icon2_4": 2,
      "Image12_17": 0,
      "Rectangle3_34": 1
    },
    "Header_NotasFrequencia": {
      "Icon2_17": 2,
      "Image12_23": 0,
      "Rectangle3_47": 1
    },
    "Header_NotasFrequencia_1": {
      "Icon2_21": 2,
      "Image12_27": 0,
      "Rectangle3_54": 1
    },
    "Header_NotasFrequencia_2": {
      "Icon2_22": 2,
      "Image12_28": 0,
      "Rectangle3_56": 1
    },
    "Header_SucessoCadastro": {
      "Image12_16": 0,
      "Rectangle3_32": 1
    },
    "Header_TelaCadastro1": {
      "Image12_1": 0,
      "Rectangle3_1": 1
    },
    "Header_TelaCadastro2": {
      "Image12_2": 0,
      "Rectangle3_3": 1
    },
    "Header_TelaCadastro3": {
      "Image12_8": 0,
      "Rectangle3_16": 1
    },
    "Header_TelaLogin": {
      "Image12": 0,
      "Rectangle3": 1
    },
    "Header_Turma": {
      "Icon2_16": 2,
      "Image12_22": 0,
      "Rectangle3_45": 1
    },
    "Header_VisNotasFrequencia": {
      "Icon2_18": 2,
      "Image12_24": 0,
      "Rectangle3_49": 1
    },
    "Meu perfil": {
      "Button3_7": 1,
      "Button3_8": 5,
      "Icon3": 3,
      "Image3_2": 0,
      "Image3_3": 4,
      "Label10": 2
    },
    "Paginacao_1": {
      "Pag<_1": 3,
      "Pag>_1": 4,
      "Pag1_1": 0,
      "Pag3_1": 1,
      "Pag4_1": 2
    },
    "Paginacao_2": {
      "Pag<_2": 2,
      "Pag>_2": 3,
      "Pag3_2": 0,
      "Pag4_2": 1
    },
    "Perfil": {
      "Image16": 1,
      "Label5": 0
    },
    "Politica Privacidade": {
      "Aceito a": 0,
      "Politica de privacidade": 1,
      "Timetable": 2
    },
    "Titulo_Atividade": {
      "Image25_4": 0,
      "Label1_7": 1
    },
    "Titulo_Atividade_1": {
      "Image25_9": 0,
      "Label1_12": 1
    },
    "Titulo_Avisos": {
      "Image3_4": 1,
      "Label1_6": 0
    },
    "Titulo_Avisos_1": {
      "Image3_5": 1,
      "Label1_8": 0
    },
    "Titulo_Avisos_2": {
      "Image3_7": 1,
      "Label1_9": 0
    },
    "Titulo_Avisos_3": {
      "Image3_8": 1,
      "Label1_10": 0
    },
    "Titulo_TelaCadastro1": {
      "Image1": 0,
      "Label1": 1
    },
    "Titulo_TelaCadastro2": {
      "Image1_1": 0,
      "Label1_1": 1
    },
    "Titulo_TelaCadastro3": {
      "Image1_3": 0,
      "Label1_5": 1
    },
    "UltimasAtividades": {
      "Icon2_1": 5,
      "Label1_4": 1,
      "Label8_2": 2,
      "Label9_2": 3,
      "Label9_3": 0,
      "Rectangle1_5": 4
    }
  },
  "OrderPcfTemplate": {},
  "OrderTemplate": {},
  "OrderXMLTemplate": {
    "arrow": 9,
    "button": 5,
    "checkbox": 12,
    "combobox": 10,
    "datepicker": 11,
    "dropdown": 4,
    "form": 7,
    "gallery": 6,
    "icon": 2,
    "image": 1,
    "label": 3,
    "rectangle": 0,
    "text": 8
  },
  "OverridablePropertiesEntry": {
    "Aceito a": {},
    "App": {},
    "Arrow1": {},
    "Arrow1_1": {},
    "Arrow2": {},
    "Arrow2_1": {},
    "Atividade1": {},
    "Atividade2": {},
    "Atividades": {},
    "Aviso1": {},
    "Aviso2": {},
    "Aviso3": {},
    "Aviso4": {},
    "Button1": {},
    "Button1_1": {},
    "Button1_10": {},
    "Button1_11": {},
    "Button1_12": {},
    "Button1_13": {},
    "Button1_14": {},
    "Button1_15": {},
    "Button1_16": {},
    "Button1_17": {},
    "Button1_18": {},
    "Button1_19": {},
    "Button1_20": {},
    "Button1_4": {},
    "Button1_5": {},
    "Button1_9": {},
    "Button2": {},
    "Button3_3": {},
    "Button3_4": {},
    "Button3_5": {},
    "Button3_6": {},
    "Button3_7": {},
    "Button3_8": {},
    "Button3_9": {},
    "Button4": {},
    "Button4_1": {},
    "Button4_2": {},
    "Button4_3": {},
    "Button5": {},
    "Button5_1": {},
    "Button5_2": {},
    "Button6": {},
    "Button6_1": {},
    "Calendario": {},
    "Checkbox2": {},
    "ConfirmaEmail": {},
    "Confirmar E-mail_DataCard1": {},
    "Confirmar Senha_DataCard1": {},
    "ConfirmarSenha": {},
    "CPF_DataCard1": {},
    "Data Nascimento_DataCard1": {},
    "DataCardKey1": {},
    "DataCardKey10": {},
    "DataCardKey3": {},
    "DataCardKey4": {},
    "DataCardKey5": {},
    "DataCardKey6": {},
    "DataCardKey7": {},
    "DataCardKey8": {},
    "DataCardKey9": {},
    "DataCardValue10": {},
    "DataCardValue7": {},
    "DataCardValue8": {},
    "DataCardValue9": {},
    "DateValue1": {},
    "DigitarSenha": {},
    "E-mail": {},
    "E-mail_DataCard1": {},
    "entradaEmail": {},
    "ErrorMessage1": {},
    "ErrorMessage2": {},
    "ErrorMessage3": {},
    "ErrorMessage4": {},
    "ErrorMessage5": {},
    "ErrorMessage6": {},
    "ErrorMessage7": {},
    "ErrorMessage8": {},
    "ErrorMessage9": {},
    "Esqueci senha | Suporte": {},
    "Facebook": {},
    "Facebook_1": {},
    "Facebook_10": {},
    "Facebook_11": {},
    "Facebook_12": {},
    "Facebook_13": {},
    "Facebook_14": {},
    "Facebook_15": {},
    "Facebook_16": {},
    "Facebook_17": {},
    "Facebook_18": {},
    "Facebook_19": {},
    "Facebook_20": {},
    "Facebook_3": {},
    "Facebook_4": {},
    "Facebook_5": {},
    "Facebook_6": {},
    "Facebook_8": {},
    "Facebook_9": {},
    "Ferramentas": {},
    "Footer_Atividade": {},
    "Footer_Atividade_1": {},
    "Footer_Avisos": {},
    "Footer_Avisos_1": {},
    "Footer_Avisos_2": {},
    "Footer_Avisos_3": {},
    "Footer_Calendario": {},
    "Footer_CursoDisciplinas": {},
    "Footer_Home": {},
    "Footer_NotasFrequencia": {},
    "Footer_NotasFrequencia_1": {},
    "Footer_NotasFrequencia_2": {},
    "Footer_SucessoCadastro": {},
    "Footer_TelaCadastro": {},
    "Footer_TelaCadastro2": {},
    "Footer_TelaCadastro3": {},
    "Footer_TelaLogin": {},
    "Footer_Turma": {},
    "Footer_VisNotasFrequencia": {},
    "FormDados": {},
    "FormLogin": {},
    "Gallery1": {},
    "galleryTemplate1": {},
    "Header_Atividade": {},
    "Header_Atividade_1": {},
    "Header_Avisos": {},
    "Header_Avisos_1": {},
    "Header_Avisos_2": {},
    "Header_Avisos_3": {},
    "Header_Calendario": {},
    "Header_CursoDisciplinas": {},
    "Header_Home": {},
    "Header_NotasFrequencia": {},
    "Header_NotasFrequencia_1": {},
    "Header_NotasFrequencia_2": {},
    "Header_SucessoCadastro": {},
    "Header_TelaCadastro1": {},
    "Header_TelaCadastro2": {},
    "Header_TelaCadastro3": {},
    "Header_TelaLogin": {},
    "Header_Turma": {},
    "Header_VisNotasFrequencia": {},
    "HourValue1": {},
    "Icon1": {},
    "Icon2_1": {},
    "Icon2_13": {},
    "Icon2_14": {},
    "Icon2_15": {},
    "Icon2_16": {},
    "Icon2_17": {},
    "Icon2_18": {},
    "Icon2_19": {},
    "Icon2_2": {},
    "Icon2_20": {},
    "Icon2_21": {},
    "Icon2_22": {},
    "Icon2_23": {},
    "Icon2_24": {},
    "Icon2_25": {},
    "Icon2_3": {},
    "Icon2_4": {},
    "Icon3": {},
    "Icon3_1": {},
    "Icon4": {},
    "Image1": {},
    "Image1_1": {},
    "Image1_3": {},
    "Image12": {},
    "Image12_1": {},
    "Image12_16": {},
    "Image12_17": {},
    "Image12_19": {},
    "Image12_2": {},
    "Image12_20": {},
    "Image12_21": {},
    "Image12_22": {},
    "Image12_23": {},
    "Image12_24": {},
    "Image12_25": {},
    "Image12_26": {},
    "Image12_27": {},
    "Image12_28": {},
    "Image12_29": {},
    "Image12_30": {},
    "Image12_31": {},
    "Image12_8": {},
    "Image13": {},
    "Image16": {},
    "Image21": {},
    "Image22": {},
    "Image23": {},
    "Image24": {},
    "Image25": {},
    "Image25_1": {},
    "Image25_2": {},
    "Image25_3": {},
    "Image25_4": {},
    "Image25_5": {},
    "Image25_6": {},
    "Image25_7": {},
    "Image25_8": {},
    "Image25_9": {},
    "Image3_1": {},
    "Image3_2": {},
    "Image3_3": {},
    "Image3_4": {},
    "Image3_5": {},
    "Image3_6": {},
    "Image3_7": {},
    "Image3_8": {},
    "Image5": {},
    "Image6": {},
    "Instagram": {},
    "Instagram_1": {},
    "Instagram_10": {},
    "Instagram_11": {},
    "Instagram_12": {},
    "Instagram_13": {},
    "Instagram_14": {},
    "Instagram_15": {},
    "Instagram_16": {},
    "Instagram_17": {},
    "Instagram_18": {},
    "Instagram_19": {},
    "Instagram_20": {},
    "Instagram_3": {},
    "Instagram_4": {},
    "Instagram_5": {},
    "Instagram_6": {},
    "Instagram_8": {},
    "Instagram_9": {},
    "Já tem cadastro": {},
    "Label1": {},
    "Label1_1": {},
    "Label1_10": {},
    "Label1_11": {},
    "Label1_12": {},
    "Label1_15": {},
    "Label1_16": {},
    "Label1_17": {},
    "Label1_18": {},
    "Label1_19": {},
    "Label1_20": {},
    "Label1_21": {},
    "Label1_22": {},
    "Label1_23": {},
    "Label1_24": {},
    "Label1_4": {},
    "Label1_5": {},
    "Label1_6": {},
    "Label1_7": {},
    "Label1_8": {},
    "Label1_9": {},
    "Label10": {},
    "Label10_1": {},
    "Label12": {},
    "Label12_1": {},
    "Label13": {},
    "Label13_1": {},
    "Label14": {},
    "Label14_1": {},
    "Label15": {},
    "Label15_1": {},
    "Label17": {},
    "Label18": {},
    "Label19": {},
    "Label19_1": {},
    "Label19_2": {},
    "Label19_3": {},
    "Label19_4": {},
    "Label19_5": {},
    "Label19_6": {},
    "Label19_7": {},
    "Label2": {},
    "Label20": {},
    "Label20_1": {},
    "Label20_2": {},
    "Label20_3": {},
    "Label21": {},
    "Label21_1": {},
    "Label21_2": {},
    "Label22": {},
    "Label22_1": {},
    "Label23": {},
    "Label23_1": {},
    "Label24": {},
    "Label24_1": {},
    "Label25": {},
    "Label25_1": {},
    "Label26": {},
    "Label27": {},
    "Label28": {},
    "Label3": {},
    "Label4": {},
    "Label5": {},
    "Label6": {},
    "Label6_1": {},
    "Label6_2": {},
    "Label6_3": {},
    "Label6_4": {},
    "Label7": {},
    "Label8_2": {},
    "Label8_3": {},
    "Label8_4": {},
    "Label8_5": {},
    "Label8_6": {},
    "Label8_7": {},
    "Label9_10": {},
    "Label9_11": {},
    "Label9_2": {},
    "Label9_3": {},
    "Label9_4": {},
    "Label9_5": {},
    "Label9_6": {},
    "Label9_7": {},
    "Label9_8": {},
    "Label9_9": {},
    "lbErroConfirmaEmail": {},
    "lbErroEntradaEmail": {},
    "Linkedin": {},
    "Linkedin_1": {},
    "Linkedin_10": {},
    "Linkedin_11": {},
    "Linkedin_12": {},
    "Linkedin_13": {},
    "Linkedin_14": {},
    "Linkedin_15": {},
    "Linkedin_16": {},
    "Linkedin_17": {},
    "Linkedin_18": {},
    "Linkedin_19": {},
    "Linkedin_20": {},
    "Linkedin_3": {},
    "Linkedin_4": {},
    "Linkedin_5": {},
    "Linkedin_6": {},
    "Linkedin_8": {},
    "Linkedin_9": {},
    "lstCursos": {},
    "lstCursos_1": {},
    "lstCursos_2": {},
    "lstDisciplinas": {},
    "lstDisciplinas_1": {},
    "lstDisciplinas_2": {},
    "Meu perfil": {},
    "MinuteValue1": {},
    "MuralAvisos1": {},
    "MuralAvisos2": {},
    "Não tem cadastro": {},
    "NextArrow4": {},
    "Nome Completo_DataCard1": {},
    "Nome Social_DataCard1": {},
    "NotasFrequencia": {},
    "Pag<_1": {},
    "Pag<_2": {},
    "Pag>_1": {},
    "Pag>_2": {},
    "Pag1_1": {},
    "Pag3_1": {},
    "Pag3_2": {},
    "Pag4_1": {},
    "Pag4_2": {},
    "Paginacao_1": {},
    "Paginacao_2": {},
    "PaginaInativa": {},
    "Perfil": {},
    "Politica de privacidade": {},
    "Politica Privacidade": {},
    "Rectangle1_10": {},
    "Rectangle1_2": {},
    "Rectangle1_5": {},
    "Rectangle1_6": {},
    "Rectangle1_7": {},
    "Rectangle1_8": {},
    "Rectangle1_9": {},
    "Rectangle2": {},
    "Rectangle3": {},
    "Rectangle3_1": {},
    "Rectangle3_14": {},
    "Rectangle3_15": {},
    "Rectangle3_16": {},
    "Rectangle3_17": {},
    "Rectangle3_2": {},
    "Rectangle3_3": {},
    "Rectangle3_32": {},
    "Rectangle3_33": {},
    "Rectangle3_34": {},
    "Rectangle3_35": {},
    "Rectangle3_38": {},
    "Rectangle3_39": {},
    "Rectangle3_4": {},
    "Rectangle3_40": {},
    "Rectangle3_41": {},
    "Rectangle3_42": {},
    "Rectangle3_43": {},
    "Rectangle3_44": {},
    "Rectangle3_45": {},
    "Rectangle3_46": {},
    "Rectangle3_47": {},
    "Rectangle3_48": {},
    "Rectangle3_49": {},
    "Rectangle3_5": {},
    "Rectangle3_50": {},
    "Rectangle3_51": {},
    "Rectangle3_52": {},
    "Rectangle3_53": {},
    "Rectangle3_54": {},
    "Rectangle3_55": {},
    "Rectangle3_56": {},
    "Rectangle3_57": {},
    "Rectangle3_58": {},
    "Rectangle3_59": {},
    "Rectangle3_60": {},
    "Rectangle3_61": {},
    "Rectangle3_62": {},
    "Rectangle3_63": {},
    "Senha": {},
    "Senha_DataCard1": {},
    "SenhaIncorreta": {},
    "Separator1": {},
    "Separator5": {},
    "Sexo_DataCard1": {},
    "StarVisible1": {},
    "StarVisible2": {},
    "StarVisible3": {},
    "StarVisible4": {},
    "StarVisible5": {},
    "StarVisible6": {},
    "StarVisible7": {},
    "StarVisible8": {},
    "StarVisible9": {},
    "Subtitle4": {},
    "SucessoCadastro": {},
    "TelaAcesso": {},
    "TelaCadastro1": {},
    "TelaCadastro2": {},
    "TelaCadastro3": {},
    "TelaLogin": {},
    "TelaMenu": {},
    "TextInput1": {},
    "TextInputEmail": {},
    "TextInputSenha": {},
    "Timetable": {},
    "Title4": {},
    "Titulo_Atividade": {},
    "Titulo_Atividade_1": {},
    "Titulo_Avisos": {},
    "Titulo_Avisos_1": {},
    "Titulo_Avisos_2": {},
    "Titulo_Avisos_3": {},
    "Titulo_TelaCadastro1": {},
    "Titulo_TelaCadastro2": {},
    "Titulo_TelaCadastro3": {},
    "Todos os direitos reservados": {},
    "Todos os direitos reservados_10": {},
    "Todos os direitos reservados_11": {},
    "Todos os direitos reservados_12": {},
    "Todos os direitos reservados_13": {},
    "Todos os direitos reservados_14": {},
    "Todos os direitos reservados_15": {},
    "Todos os direitos reservados_16": {},
    "Todos os direitos reservados_17": {},
    "Todos os direitos reservados_18": {},
    "Todos os direitos reservados_19": {},
    "Todos os direitos reservados_2": {},
    "Todos os direitos reservados_20": {},
    "Todos os direitos reservados_21": {},
    "Todos os direitos reservados_22": {},
    "Todos os direitos reservados_3": {},
    "Todos os direitos reservados_5": {},
    "Todos os direitos reservados_6": {},
    "Todos os direitos reservados_7": {},
    "Todos os direitos reservados_8": {},
    "TurmaInativa": {},
    "Twitter": {},
    "Twitter_1": {},
    "Twitter_10": {},
    "Twitter_11": {},
    "Twitter_12": {},
    "Twitter_13": {},
    "Twitter_14": {},
    "Twitter_15": {},
    "Twitter_16": {},
    "Twitter_17": {},
    "Twitter_18": {},
    "Twitter_19": {},
    "Twitter_20": {},
    "Twitter_3": {},
    "Twitter_4": {},
    "Twitter_5": {},
    "Twitter_6": {},
    "Twitter_8": {},
    "Twitter_9": {},
    "TxtCep": {},
    "TxtCep_1": {},
    "TxtCep_2": {},
    "TxtCep_3": {},
    "TxtCep_4": {},
    "TxtCep_5": {},
    "UltimasAtividades": {},
    "Visualizar Notas e Frequência": {},
    "Youtube": {},
    "Youtube_1": {},
    "Youtube_10": {},
    "Youtube_11": {},
    "Youtube_12": {},
    "Youtube_13": {},
    "Youtube_14": {},
    "Youtube_15": {},
    "Youtube_16": {},
    "Youtube_17": {},
    "Youtube_18": {},
    "Youtube_19": {},
    "Youtube_20": {},
    "Youtube_3": {},
    "Youtube_4": {},
    "Youtube_5": {},
    "Youtube_6": {},
    "Youtube_8": {},
    "Youtube_9": {}
  },
  "PCFDynamicSchemaForIRRetrievalEntry": {},
  "PublishOrderIndices": {
    "Aceito a": 130,
    "App": 0,
    "Arrow1": 54,
    "Arrow1_1": 99,
    "Arrow2": 98,
    "Arrow2_1": 135,
    "Atividade1": 0,
    "Atividade2": 0,
    "Atividades": 0,
    "Aviso1": 0,
    "Aviso2": 0,
    "Aviso3": 0,
    "Aviso4": 0,
    "Button1": 2,
    "Button1_1": 4,
    "Button1_10": 451,
    "Button1_11": 204,
    "Button1_12": 253,
    "Button1_13": 432,
    "Button1_14": 323,
    "Button1_15": 155,
    "Button1_16": 493,
    "Button1_17": 342,
    "Button1_18": 391,
    "Button1_19": 411,
    "Button1_20": 274,
    "Button1_4": 15,
    "Button1_5": 134,
    "Button1_9": 471,
    "Button2": 148,
    "Button3_3": 182,
    "Button3_4": 184,
    "Button3_5": 186,
    "Button3_6": 189,
    "Button3_7": 174,
    "Button3_8": 176,
    "Button3_9": 192,
    "Button4": 292,
    "Button4_1": 296,
    "Button4_2": 364,
    "Button4_3": 360,
    "Button5": 368,
    "Button5_1": 303,
    "Button5_2": 371,
    "Button6": 224,
    "Button6_1": 232,
    "Calendario": 0,
    "Checkbox2": 129,
    "ConfirmaEmail": 40,
    "Confirmar E-mail_DataCard1": 37,
    "Confirmar Senha_DataCard1": 47,
    "ConfirmarSenha": 50,
    "CPF_DataCard1": 80,
    "Data Nascimento_DataCard1": 90,
    "DataCardKey1": 92,
    "DataCardKey10": 87,
    "DataCardKey3": 39,
    "DataCardKey4": 49,
    "DataCardKey5": 44,
    "DataCardKey6": 34,
    "DataCardKey7": 72,
    "DataCardKey8": 77,
    "DataCardKey9": 82,
    "DataCardValue10": 88,
    "DataCardValue7": 73,
    "DataCardValue8": 78,
    "DataCardValue9": 83,
    "DateValue1": 93,
    "DigitarSenha": 45,
    "E-mail": 10,
    "E-mail_DataCard1": 32,
    "entradaEmail": 35,
    "ErrorMessage1": 97,
    "ErrorMessage2": 41,
    "ErrorMessage3": 51,
    "ErrorMessage4": 46,
    "ErrorMessage5": 36,
    "ErrorMessage6": 74,
    "ErrorMessage7": 79,
    "ErrorMessage8": 84,
    "ErrorMessage9": 89,
    "Esqueci senha | Suporte": 16,
    "Facebook": 19,
    "Facebook_1": 57,
    "Facebook_10": 474,
    "Facebook_11": 454,
    "Facebook_12": 207,
    "Facebook_13": 496,
    "Facebook_14": 435,
    "Facebook_15": 345,
    "Facebook_16": 306,
    "Facebook_17": 374,
    "Facebook_18": 394,
    "Facebook_19": 414,
    "Facebook_20": 277,
    "Facebook_3": 102,
    "Facebook_4": 138,
    "Facebook_5": 158,
    "Facebook_6": 235,
    "Facebook_8": 326,
    "Facebook_9": 256,
    "Ferramentas": 188,
    "Footer_Atividade": 255,
    "Footer_Atividade_1": 276,
    "Footer_Avisos": 325,
    "Footer_Avisos_1": 344,
    "Footer_Avisos_2": 393,
    "Footer_Avisos_3": 413,
    "Footer_Calendario": 434,
    "Footer_CursoDisciplinas": 473,
    "Footer_Home": 234,
    "Footer_NotasFrequencia": 206,
    "Footer_NotasFrequencia_1": 305,
    "Footer_NotasFrequencia_2": 373,
    "Footer_SucessoCadastro": 157,
    "Footer_TelaCadastro": 56,
    "Footer_TelaCadastro2": 101,
    "Footer_TelaCadastro3": 137,
    "Footer_TelaLogin": 18,
    "Footer_Turma": 453,
    "Footer_VisNotasFrequencia": 495,
    "FormDados": 69,
    "FormLogin": 31,
    "Gallery1": 426,
    "galleryTemplate1": 427,
    "Header_Atividade": 242,
    "Header_Atividade_1": 263,
    "Header_Avisos": 313,
    "Header_Avisos_1": 333,
    "Header_Avisos_2": 381,
    "Header_Avisos_3": 401,
    "Header_Calendario": 421,
    "Header_CursoDisciplinas": 461,
    "Header_Home": 214,
    "Header_NotasFrequencia": 194,
    "Header_NotasFrequencia_1": 284,
    "Header_NotasFrequencia_2": 352,
    "Header_SucessoCadastro": 146,
    "Header_TelaCadastro1": 26,
    "Header_TelaCadastro2": 64,
    "Header_TelaCadastro3": 109,
    "Header_TelaLogin": 7,
    "Header_Turma": 442,
    "Header_VisNotasFrequencia": 481,
    "HourValue1": 94,
    "Icon1": 118,
    "Icon2_1": 230,
    "Icon2_13": 315,
    "Icon2_14": 244,
    "Icon2_15": 463,
    "Icon2_16": 444,
    "Icon2_17": 196,
    "Icon2_18": 483,
    "Icon2_19": 423,
    "Icon2_2": 217,
    "Icon2_20": 335,
    "Icon2_21": 286,
    "Icon2_22": 354,
    "Icon2_23": 383,
    "Icon2_24": 403,
    "Icon2_25": 265,
    "Icon2_3": 222,
    "Icon2_4": 216,
    "Icon3": 172,
    "Icon3_1": 178,
    "Icon4": 166,
    "Image1": 30,
    "Image1_1": 68,
    "Image1_3": 113,
    "Image12": 8,
    "Image12_1": 27,
    "Image12_16": 145,
    "Image12_17": 215,
    "Image12_19": 314,
    "Image12_2": 65,
    "Image12_20": 243,
    "Image12_21": 462,
    "Image12_22": 443,
    "Image12_23": 195,
    "Image12_24": 482,
    "Image12_25": 422,
    "Image12_26": 334,
    "Image12_27": 285,
    "Image12_28": 353,
    "Image12_29": 382,
    "Image12_30": 402,
    "Image12_31": 264,
    "Image12_8": 110,
    "Image13": 9,
    "Image16": 167,
    "Image21": 181,
    "Image22": 183,
    "Image23": 185,
    "Image24": 187,
    "Image25": 465,
    "Image25_1": 468,
    "Image25_2": 445,
    "Image25_3": 198,
    "Image25_4": 247,
    "Image25_5": 424,
    "Image25_6": 149,
    "Image25_7": 485,
    "Image25_8": 152,
    "Image25_9": 268,
    "Image3_1": 287,
    "Image3_2": 173,
    "Image3_3": 175,
    "Image3_4": 318,
    "Image3_5": 338,
    "Image3_6": 355,
    "Image3_7": 386,
    "Image3_8": 406,
    "Image5": 191,
    "Image6": 0,
    "Instagram": 20,
    "Instagram_1": 58,
    "Instagram_10": 475,
    "Instagram_11": 455,
    "Instagram_12": 208,
    "Instagram_13": 497,
    "Instagram_14": 436,
    "Instagram_15": 346,
    "Instagram_16": 307,
    "Instagram_17": 375,
    "Instagram_18": 395,
    "Instagram_19": 415,
    "Instagram_20": 278,
    "Instagram_3": 103,
    "Instagram_4": 139,
    "Instagram_5": 159,
    "Instagram_6": 236,
    "Instagram_8": 327,
    "Instagram_9": 257,
    "Já tem cadastro": 1,
    "Label1": 29,
    "Label1_1": 67,
    "Label1_10": 405,
    "Label1_11": 218,
    "Label1_12": 267,
    "Label1_15": 469,
    "Label1_16": 446,
    "Label1_17": 197,
    "Label1_18": 288,
    "Label1_19": 425,
    "Label1_20": 356,
    "Label1_21": 484,
    "Label1_22": 466,
    "Label1_23": 150,
    "Label1_24": 153,
    "Label1_4": 226,
    "Label1_5": 112,
    "Label1_6": 317,
    "Label1_7": 246,
    "Label1_8": 337,
    "Label1_9": 385,
    "Label10": 171,
    "Label10_1": 177,
    "Label12": 199,
    "Label12_1": 487,
    "Label13": 200,
    "Label13_1": 488,
    "Label14": 201,
    "Label14_1": 490,
    "Label15": 202,
    "Label15_1": 491,
    "Label17": 486,
    "Label18": 489,
    "Label19": 321,
    "Label19_1": 319,
    "Label19_2": 339,
    "Label19_3": 341,
    "Label19_4": 387,
    "Label19_5": 389,
    "Label19_6": 407,
    "Label19_7": 409,
    "Label2": 116,
    "Label20": 320,
    "Label20_1": 340,
    "Label20_2": 388,
    "Label20_3": 408,
    "Label21": 322,
    "Label21_1": 390,
    "Label21_2": 410,
    "Label22": 252,
    "Label22_1": 273,
    "Label23": 251,
    "Label23_1": 272,
    "Label24": 250,
    "Label24_1": 271,
    "Label25": 248,
    "Label25_1": 269,
    "Label26": 447,
    "Label27": 448,
    "Label28": 449,
    "Label3": 147,
    "Label4": 114,
    "Label5": 169,
    "Label6": 119,
    "Label6_1": 120,
    "Label6_2": 123,
    "Label6_3": 125,
    "Label6_4": 126,
    "Label7": 464,
    "Label8_2": 229,
    "Label8_3": 221,
    "Label8_4": 290,
    "Label8_5": 294,
    "Label8_6": 358,
    "Label8_7": 362,
    "Label9_10": 223,
    "Label9_11": 270,
    "Label9_2": 231,
    "Label9_3": 228,
    "Label9_4": 220,
    "Label9_5": 249,
    "Label9_6": 291,
    "Label9_7": 295,
    "Label9_8": 363,
    "Label9_9": 359,
    "lbErroConfirmaEmail": 53,
    "lbErroEntradaEmail": 52,
    "Linkedin": 21,
    "Linkedin_1": 59,
    "Linkedin_10": 476,
    "Linkedin_11": 456,
    "Linkedin_12": 209,
    "Linkedin_13": 498,
    "Linkedin_14": 437,
    "Linkedin_15": 347,
    "Linkedin_16": 308,
    "Linkedin_17": 376,
    "Linkedin_18": 396,
    "Linkedin_19": 416,
    "Linkedin_20": 279,
    "Linkedin_3": 104,
    "Linkedin_4": 140,
    "Linkedin_5": 160,
    "Linkedin_6": 237,
    "Linkedin_8": 328,
    "Linkedin_9": 258,
    "lstCursos": 467,
    "lstCursos_1": 450,
    "lstCursos_2": 151,
    "lstDisciplinas": 470,
    "lstDisciplinas_1": 203,
    "lstDisciplinas_2": 154,
    "Meu perfil": 170,
    "MinuteValue1": 96,
    "MuralAvisos1": 0,
    "MuralAvisos2": 0,
    "Não tem cadastro": 3,
    "NextArrow4": 429,
    "Nome Completo_DataCard1": 70,
    "Nome Social_DataCard1": 75,
    "NotasFrequencia": 0,
    "Pag<_1": 297,
    "Pag<_2": 365,
    "Pag>_1": 300,
    "Pag>_2": 367,
    "Pag1_1": 299,
    "Pag3_1": 301,
    "Pag3_2": 369,
    "Pag4_1": 302,
    "Pag4_2": 370,
    "Paginacao_1": 298,
    "Paginacao_2": 366,
    "PaginaInativa": 0,
    "Perfil": 168,
    "Politica de privacidade": 132,
    "Politica Privacidade": 131,
    "Rectangle1_10": 219,
    "Rectangle1_2": 492,
    "Rectangle1_5": 227,
    "Rectangle1_6": 289,
    "Rectangle1_7": 357,
    "Rectangle1_8": 293,
    "Rectangle1_9": 361,
    "Rectangle2": 165,
    "Rectangle3": 6,
    "Rectangle3_1": 25,
    "Rectangle3_14": 164,
    "Rectangle3_15": 190,
    "Rectangle3_16": 108,
    "Rectangle3_17": 136,
    "Rectangle3_2": 17,
    "Rectangle3_3": 63,
    "Rectangle3_32": 144,
    "Rectangle3_33": 156,
    "Rectangle3_34": 213,
    "Rectangle3_35": 233,
    "Rectangle3_38": 324,
    "Rectangle3_39": 312,
    "Rectangle3_4": 55,
    "Rectangle3_40": 254,
    "Rectangle3_41": 241,
    "Rectangle3_42": 472,
    "Rectangle3_43": 460,
    "Rectangle3_44": 452,
    "Rectangle3_45": 441,
    "Rectangle3_46": 205,
    "Rectangle3_47": 193,
    "Rectangle3_48": 494,
    "Rectangle3_49": 480,
    "Rectangle3_5": 100,
    "Rectangle3_50": 433,
    "Rectangle3_51": 420,
    "Rectangle3_52": 332,
    "Rectangle3_53": 343,
    "Rectangle3_54": 283,
    "Rectangle3_55": 304,
    "Rectangle3_56": 351,
    "Rectangle3_57": 372,
    "Rectangle3_58": 380,
    "Rectangle3_59": 392,
    "Rectangle3_60": 400,
    "Rectangle3_61": 412,
    "Rectangle3_62": 262,
    "Rectangle3_63": 275,
    "Senha": 12,
    "Senha_DataCard1": 42,
    "SenhaIncorreta": 14,
    "Separator1": 95,
    "Separator5": 431,
    "Sexo_DataCard1": 85,
    "StarVisible1": 91,
    "StarVisible2": 38,
    "StarVisible3": 48,
    "StarVisible4": 43,
    "StarVisible5": 33,
    "StarVisible6": 71,
    "StarVisible7": 76,
    "StarVisible8": 81,
    "StarVisible9": 86,
    "Subtitle4": 430,
    "SucessoCadastro": 0,
    "TelaAcesso": 0,
    "TelaCadastro1": 0,
    "TelaCadastro2": 0,
    "TelaCadastro3": 0,
    "TelaLogin": 0,
    "TelaMenu": 0,
    "TextInput1": 115,
    "TextInputEmail": 11,
    "TextInputSenha": 13,
    "Timetable": 133,
    "Title4": 428,
    "Titulo_Atividade": 245,
    "Titulo_Atividade_1": 266,
    "Titulo_Avisos": 316,
    "Titulo_Avisos_1": 336,
    "Titulo_Avisos_2": 384,
    "Titulo_Avisos_3": 404,
    "Titulo_TelaCadastro1": 28,
    "Titulo_TelaCadastro2": 66,
    "Titulo_TelaCadastro3": 111,
    "Todos os direitos reservados": 5,
    "Todos os direitos reservados_10": 331,
    "Todos os direitos reservados_11": 261,
    "Todos os direitos reservados_12": 479,
    "Todos os direitos reservados_13": 459,
    "Todos os direitos reservados_14": 212,
    "Todos os direitos reservados_15": 501,
    "Todos os direitos reservados_16": 440,
    "Todos os direitos reservados_17": 350,
    "Todos os direitos reservados_18": 311,
    "Todos os direitos reservados_19": 379,
    "Todos os direitos reservados_2": 24,
    "Todos os direitos reservados_20": 399,
    "Todos os direitos reservados_21": 419,
    "Todos os direitos reservados_22": 282,
    "Todos os direitos reservados_3": 62,
    "Todos os direitos reservados_5": 107,
    "Todos os direitos reservados_6": 143,
    "Todos os direitos reservados_7": 163,
    "Todos os direitos reservados_8": 240,
    "TurmaInativa": 0,
    "Twitter": 23,
    "Twitter_1": 61,
    "Twitter_10": 478,
    "Twitter_11": 458,
    "Twitter_12": 211,
    "Twitter_13": 500,
    "Twitter_14": 439,
    "Twitter_15": 349,
    "Twitter_16": 310,
    "Twitter_17": 378,
    "Twitter_18": 398,
    "Twitter_19": 418,
    "Twitter_20": 281,
    "Twitter_3": 106,
    "Twitter_4": 142,
    "Twitter_5": 162,
    "Twitter_6": 239,
    "Twitter_8": 330,
    "Twitter_9": 260,
    "TxtCep": 117,
    "TxtCep_1": 121,
    "TxtCep_2": 124,
    "TxtCep_3": 122,
    "TxtCep_4": 127,
    "TxtCep_5": 128,
    "UltimasAtividades": 225,
    "Visualizar Notas e Frequência": 0,
    "Youtube": 22,
    "Youtube_1": 60,
    "Youtube_10": 477,
    "Youtube_11": 457,
    "Youtube_12": 210,
    "Youtube_13": 499,
    "Youtube_14": 438,
    "Youtube_15": 348,
    "Youtube_16": 309,
    "Youtube_17": 377,
    "Youtube_18": 397,
    "Youtube_19": 417,
    "Youtube_20": 280,
    "Youtube_3": 105,
    "Youtube_4": 141,
    "Youtube_5": 161,
    "Youtube_6": 238,
    "Youtube_8": 329,
    "Youtube_9": 259
  },
  "ResourcesJsonIndices": {
    "Image-10": 20,
    "Image-18": 18,
    "Image-19 1": 41,
    "Image-2": 3,
    "Image-2_1": 4,
    "Image-20": 27,
    "Image-24": 21,
    "Image-25": 28,
    "Image-26": 31,
    "Image-27": 15,
    "Image-28": 33,
    "Image-29": 30,
    "Image-32": 32,
    "Image-7": 29,
    "Image-bg-btn": 10,
    "Image-bg-btn_1": 13,
    "Image-Ellipse 1": 25,
    "Image-EnsinoSuperior": 26,
    "Image-Esqueci a senha _ Suporte login": 34,
    "Image-Footer": 7,
    "Image-FooterIcones": 22,
    "Image-Group 3": 9,
    "Image-Group 3_1": 19,
    "Image-Header liso": 5,
    "Image-icon1": 1,
    "Image-icons8-facebook-90": 36,
    "Image-icons8-instagram-128": 37,
    "Image-icons8-linkedin-128": 38,
    "Image-icons8-twitter-squared-64": 40,
    "Image-icons8-youtube-squared-128": 39,
    "Image-Já tem cadastro_": 11,
    "Image-meuperfil": 24,
    "Image-Não tem cadastro_": 12,
    "Image-NATAL 2022": 8,
    "Image-NATAL 2022_1": 14,
    "Image-partebaixo": 2,
    "Image-privacidade": 35,
    "Image-Rectangle 26": 6,
    "Image-Rectangle 27": 23,
    "Image-SampleImage": 0,
    "Image-Section 3": 17,
    "Image-Todos os Direitos Reservados - 2022": 16
  },
  "RuleScreenIdWithoutScreen": {},
  "TemplateVersions": {},
  "VolatileProperties": {
    "AnalysisLoadTime": 1.9816224,
    "ControlCount": {
      "arrow": 4,
      "button": 39,
      "checkbox": 1,
      "combobox": 1,
      "datepicker": 1,
      "dropdown": 9,
      "form": 2,
      "gallery": 1,
      "galleryTemplate": 1,
      "group": 63,
      "icon": 26,
      "image": 155,
      "label": 185,
      "rectangle": 60,
      "screen": 22,
      "text": 17,
      "typedDataCard": 9
    },
    "DeserializationLoadTime": 5.0107547,
    "ErrorCount": 0
  },
  "WasLocalDatabaseReferencesEmpty": false
}