{
  "FormatVersion": "0.24",
  "Header": {
    "DocVersion": "1.330",
    "MinVersionToLoad": "1.327",
    "MSAppStructureVersion": "2.0"
  },
  "Properties": {
    "AppCreationSource": "AppFromScratch",
    "AppDescription": "Aplicativo de uso acadêmico para melhor organização da agenda do aluno.",
    "AppPreviewFlagsMap": {
      "aibuilderserviceenrollment": false,
      "allowmultiplescreensincanvaspages": false,
      "appinsightserrortracing": false,
      "appinstrumentationcorrelationtracing": false,
      "autocreateenvironmentvariables": false,
      "backfromhostaction": false,
      "behaviorpropertyui": false,
      "blockmovingcontrol": true,
      "cdsdataformatting": false,
      "classiccontrols": false,
      "consistentreturnschemafortabularfunctions": true,
      "copyandmerge": true,
      "datatablev2control": true,
      "dataverseactionsenabled": false,
      "delaycontrolrendering": true,
      "delayloadscreens": true,
      "disablecdsfileandlargeimage": false,
      "dynamicschema": false,
      "enableactionenhancedcomponentproperties": false,
      "enableappembeddingux": false,
      "enablebarcodereaderfeature": false,
      "enablechatbotfeature": false,
      "enablecomponentnamemaps": false,
      "enablecomponentscopeoldbehavior": false,
      "enabledataanalyzercontrol": false,
      "enableeditcacherefreshfrequency": false,
      "enableexcelonlinebusinessv2connector": true,
      "enableideaspanel": true,
      "enableonstart": true,
      "enableonstartnavigate": false,
      "enablepcfmoderndatasets": true,
      "enablepowerautomatepane": true,
      "enablerowscopeonetonexpand": false,
      "enablerpawarecomponentdependency": true,
      "enablerulespanel": false,
      "enableruntimepolicies": false,
      "enablesaveloadcleardataonweb": false,
      "enhancedcomponentfunctionproperty": false,
      "enhanceddelegation": true,
      "enhancedgalleryinitialization": true,
      "errorhandling": true,
      "excelcompatibility": false,
      "expandedsavedatasupport": true,
      "exportimportcomponents2": true,
      "externalmessage": false,
      "fluentv9controls": false,
      "formuladataprefetch": true,
      "formularepair": true,
      "generatedebugpublishedapp": false,
      "herocontrols": false,
      "improvedmediacapture": false,
      "improvedtabstopbehavior": false,
      "keeprecentscreensloaded": false,
      "longlivingcache": false,
      "namedformulas": false,
      "nativecdsexperimental": true,
      "optimizedforteamsmeeting": false,
      "packagemodernruntime": false,
      "parallelcodegen": false,
      "pdffunction": false,
      "projectionmapping": true,
      "reactformulabar": false,
      "reliableconcurrent": true,
      "reverttooldpowerautomate": false,
      "rtlinstudiopreview": false,
      "rtlsupport": false,
      "supportcolumnnamesasidentifiers": false,
      "tabledoesntwraprecords": true,
      "untypedobject": false,
      "usedisplaynamemetadata": true,
      "useenforcesavedatalimits": true,
      "useexperimentalcdsconnector": true,
      "useexperimentalsqlconnector": true,
      "useguiddatatypes": true,
      "usenonblockingonstartrule": true,
      "webbarcodescanner": false,
      "zeroalltabindexes": false
    },
    "Author": "",
    "ContainsThirdPartyPcfControls": false,
    "DefaultConnectedDataSourceMaxGetRowsCount": 500,
    "DocumentAppType": "Phone",
    "DocumentLayoutHeight": 1136,
    "DocumentLayoutLockOrientation": false,
    "DocumentLayoutMaintainAspectRatio": true,
    "DocumentLayoutOrientation": "portrait",
    "DocumentLayoutScaleToFit": true,
    "DocumentLayoutWidth": 640,
    "DocumentType": "App",
    "EnableInstrumentation": false,
    "FileID": "ea75fb8b-ef4b-40b3-ad72-09c54f69ab81",
    "Id": "ea75fb8b-ef4b-40b3-ad72-09c54f69ab81",
    "InstrumentationKey": "",
    "Name": "TimeTable",
    "OriginatingVersion": "1.327"
  },
  "PublishInfo": {
    "AppName": "TimeTable",
    "BackgroundColor": "rgba(122, 229, 130, 1)",
    "IconColor": "RGBA(255,255,255,1)",
    "IconName": "",
    "LogoFileName": "logo.jpg",
    "PublishDataLocally": false,
    "PublishResourcesLocally": false,
    "PublishTarget": "player",
    "UserLocale": "pt-BR"
  },
  "ScreenOrder": [
    "TelaAcesso",
    "TelaLogin",
    "TelaCadastro1",
    "TelaCadastro2",
    "TelaCadastro3",
    "SucessoCadastro",
    "TelaMenu",
    "NotasFrequencia",
    "Atividades",
    "Atividade1",
    "Atividade2",
    "MuralAvisos1",
    "Aviso1",
    "Aviso2",
    "MuralAvisos2",
    "Aviso3",
    "Aviso4",
    "Calendario",
    "TurmaInativa",
    "PaginaInativa",
    "Visualizar Notas e Frequência"
  ]
}